Workbook
Name lista_aforadores: LISTAS!$A$1:$A$1000
Name lista_clientes: LISTAS!$B$1:$B$1000
Name lista_tipo_gasto: LISTAS!$D$1:$D$1000
Name OsTransferencias: LISTAS!$E$2:$E$1000
Name lista_bancos: LISTAS!$C$1:$C$1000
Name ListaOS: 'BASE OS'!$A$2:$A$1000
Name lista_tipo_factura: LISTAS!$F$2:$F$1000
Name lista_tipo_pago: LISTAS!$G$2:$G$1000

Sheet PANEL PRINCIPAL
A1: PANEL PRINCIPAL DE GESTIÓN OS
A3: GENERADOR DE OS
A4: Próxima OS | F4: =CONCATENATE(TEXT(COUNTIF('BASE OS'!A:A,"*-"&TEXT(YEAR(TODAY()),"0000"))+1,"000"),"-",TEXT(YEAR(TODAY()),"0000")) -> 001-2025
A6: RESUMEN DEL DÍA
A7: Os Pendientes | F7: =COUNTIF('BASE OS'!I:I,"No") -> 5
A8: Transferencias Hoy | F8: =COUNTIF('BASE TRANSFERENCIAS'!K:K,TODAY()) -> 0
A10: =IFERROR(__xludf.DUMMYFUNCTION("QUERY( 'BASE OS'!A:I, ""SELECT A, B, E, F, G, I ORDER BY A DESC LIMIT 5"", 1 )"),"OS") -> OS | B10: =IFERROR(__xludf.DUMMYFUNCTION("""COMPUTED_VALUE"""),"CLIENTE") -> CLIENTE | C10: =IFERROR(__xludf.DUMMYFUNCTION("""COMPUTED_VALUE"""),"AFORADOR") -> AFORADOR | D10: =IFERROR(__xludf.DUMMYFUNCTION("""COMPUTED_VALUE"""),"REFERENCIA / BL") -> REFERENCIA / BL | E10: =IFERROR(__xludf.DUMMYFUNCTION("""COMPUTED_VALUE"""),"FECHA") -> FECHA | F10: =IFERROR(__xludf.DUMMYFUNCTION("""COMPUTED_VALUE"""),"FACTURADO") -> FACTURADO
A11: =IFERROR(__xludf.DUMMYFUNCTION("""COMPUTED_VALUE"""),"008-2024") -> 008-2024 | B11: =IFERROR(__xludf.DUMMYFUNCTION("""COMPUTED_VALUE"""),"QUIMICA INDUSTRIAL") -> QUIMICA INDUSTRIAL | C11: =IFERROR(__xludf.DUMMYFUNCTION("""COMPUTED_VALUE"""),"ROBERTO") -> ROBERTO | D11: =IFERROR(__xludf.DUMMYFUNCTION("""COMPUTED_VALUE"""),"146-28394") -> 146-28394 | E11: =IFERROR(__xludf.DUMMYFUNCTION("""COMPUTED_VALUE"""),45609.0) -> 45609 | F11: =IFERROR(__xludf.DUMMYFUNCTION("""COMPUTED_VALUE"""),"No") -> No
A12: =IFERROR(__xludf.DUMMYFUNCTION("""COMPUTED_VALUE"""),"007-2024") -> 007-2024 | B12: =IFERROR(__xludf.DUMMYFUNCTION("""COMPUTED_VALUE"""),"AISAL") -> AISAL | C12: =IFERROR(__xludf.DUMMYFUNCTION("""COMPUTED_VALUE"""),"MARÍA JOSE") -> MARÍA JOSE | D12: =IFERROR(__xludf.DUMMYFUNCTION("""COMPUTED_VALUE"""),"146-34599") -> 146-34599 | E12: =IFERROR(__xludf.DUMMYFUNCTION("""COMPUTED_VALUE"""),45608.0) -> 45608 | F12: =IFERROR(__xludf.DUMMYFUNCTION("""COMPUTED_VALUE"""),"No") -> No
A13: =IFERROR(__xludf.DUMMYFUNCTION("""COMPUTED_VALUE"""),"006-2024") -> 006-2024 | B13: =IFERROR(__xludf.DUMMYFUNCTION("""COMPUTED_VALUE"""),"GEVI") -> GEVI | C13: =IFERROR(__xludf.DUMMYFUNCTION("""COMPUTED_VALUE"""),"GLENDA CAÑAS") -> GLENDA CAÑAS | D13: =IFERROR(__xludf.DUMMYFUNCTION("""COMPUTED_VALUE"""),"146-34251") -> 146-34251 | E13: =IFERROR(__xludf.DUMMYFUNCTION("""COMPUTED_VALUE"""),45607.0) -> 45607 | F13: =IFERROR(__xludf.DUMMYFUNCTION("""COMPUTED_VALUE"""),"No") -> No
A14: =IFERROR(__xludf.DUMMYFUNCTION("""COMPUTED_VALUE"""),"005-2024") -> 005-2024 | B14: =IFERROR(__xludf.DUMMYFUNCTION("""COMPUTED_VALUE"""),"AISAL") -> AISAL | C14: =IFERROR(__xludf.DUMMYFUNCTION("""COMPUTED_VALUE"""),"MARÍA JOSE") -> MARÍA JOSE | D14: =IFERROR(__xludf.DUMMYFUNCTION("""COMPUTED_VALUE"""),"146-34223") -> 146-34223 | E14: =IFERROR(__xludf.DUMMYFUNCTION("""COMPUTED_VALUE"""),45607.0) -> 45607 | F14: =IFERROR(__xludf.DUMMYFUNCTION("""COMPUTED_VALUE"""),"No") -> No
A15: =IFERROR(__xludf.DUMMYFUNCTION("""COMPUTED_VALUE"""),"004-2024") -> 004-2024 | B15: =IFERROR(__xludf.DUMMYFUNCTION("""COMPUTED_VALUE"""),"DIGICEL") -> DIGICEL | C15: =IFERROR(__xludf.DUMMYFUNCTION("""COMPUTED_VALUE"""),"ROBERTO") -> ROBERTO | D15: =IFERROR(__xludf.DUMMYFUNCTION("""COMPUTED_VALUE"""),"146-29934") -> 146-29934 | E15: =IFERROR(__xludf.DUMMYFUNCTION("""COMPUTED_VALUE"""),45606.0) -> 45606 | F15: =IFERROR(__xludf.DUMMYFUNCTION("""COMPUTED_VALUE"""),"No") -> No

Sheet REGISTRO OS
B1: REGISTRO DE NUEVA OS
C3: Número OS | E3: =CONCATENATE( TEXT( COUNTIF( 'BASE OS'!A:A, "*-"&TEXT(YEAR(TODAY()),"0000") )+1, "000" ), "-", TEXT(YEAR(TODAY()),"0000") ) -> 001-2025 | G3: Vista Previa
C5: Cliente | E5: TRANSTAINER | G5: OS: | H5: =E3 -> 001-2025
G6: Cliente: | H6: =E5 -> TRANSTAINER
C7: Sub - Cliente | E7: N/A | G7: Sub - Cliente: | H7: =E7 -> N/A
G8: DUCA / Servicio: | H8: =E9 -> 4-16283
C9: DUCA / Servicio | E9: 4-16283 | G9: Aforador: | H9: =E11 -> GLENDA CAÑAS
G10: Referencia / BL: | H10: =E13 -> 146-25382
C11: Aforador | E11: GLENDA CAÑAS | G11: Fecha: | H11: =E15 -> 45621
C13: Referencia / BL | E13: 146-25382
C15: Fecha | E15: 45621

Sheet BASE OS
A1: OS | B1: CLIENTE | C1: SUB CLIENTE | D1: DUCA - SERVICIO | E1: AFORADOR | F1: REFERENCIA / BL | G1: FECHA | H1: MES | I1: FACTURADO
A2: 001-2024 | B2: PANADERIA SINAI | C2: N/A | D2: 4-38493 | E2: ADELAYDA | F2: 146-28394 | G2: 45606 | H2: NOVIEMBRE | I2: Sí
A3: 002-2024 | B3: PINTO Y COMPANIA | C3: N/A | D3: 4-28394 | E3: ADELAYDA | F3: 146-28394 | G3: 45606 | H3: NOVIEMBRE | I3: Sí
A4: 003-2024 | B4: DIVACO | C4: N/A | D4: 4-23934 | E4: GLENDA CAÑAS | F4: 146-33843 | G4: 45606 | H4: NOVIEMBRE | I4: Sí
A5: 004-2024 | B5: DIGICEL | C5: N/A | D5: 4-29394 | E5: ROBERTO | F5: 146-29934 | G5: 45606 | H5: NOVIEMBRE | I5: No
A6: 005-2024 | B6: AISAL | C6: N/A | D6: 4-22567 | E6: MARÍA JOSE | F6: 146-34223 | G6: 45607 | H6: NOVIEMBRE | I6: No
A7: 006-2024 | B7: GEVI | C7: N/A | D7: 4-35685 | E7: GLENDA CAÑAS | F7: 146-34251 | G7: 45607 | H7: NOVIEMBRE | I7: No
A8: 007-2024 | B8: AISAL | C8: N/A | D8: 4-35969 | E8: MARÍA JOSE | F8: 146-34599 | G8: 45608 | H8: NOVIEMBRE | I8: No
A9: 008-2024 | B9: QUIMICA INDUSTRIAL | C9: N/A | D9: 4-38492 | E9: ROBERTO | F9: 146-28394 | G9: 45609 | H9: NOVIEMBRE | I9: No | J9: TRUE | K9: Proteger registro

Sheet REGISTRO TRANSFERENCIAS
B1: REGISTRO DE TRANSFERENCIAS
C3: Número OS
C5: Cliente
C7: A Nombre De
C9: Detalle
C11: Monto
C13: Solicitado Por
C15: Banco
C17: Tipo de Gasto
C19: Fecha

Sheet BASE TRANSFERENCIAS
A1: OS | B1: CLIENTE | C1: SUB CLIENTE | D1: A NOMBRE DE | E1: DETALLE | F1: CCF | G1: MONTO | H1: SOLICITADO POR | I1: BANCO | J1: TIPO | K1: FECHA | L1: MES
A2: 001-2024 | B2: PANADERIA SINAI | C2: N/A | D2: M.H | E2: IMPUESTOS | G2: 33.284 | H2: MARÍA JOSE | I2: AGRICOLA | J2: CARGOS A CLIENTES | K2: 45606 | L2: =IF(ISBLANK(K2),"",UPPER(TEXT(K2,"MMMM"))) -> NOVIEMBRE
A3: 006-2024 | B3: GEVI | C3: N/A | D3: M.H | E3: IMPUESTOS | G3: 125.588 | H3: GLENDA CAÑAS | I3: AGRICOLA | J3: CARGOS A CLIENTES | K3: 45608 | L3: =IF(ISBLANK(K3),"",UPPER(TEXT(K3,"MMMM"))) -> NOVIEMBRE
A4: 008-2024 | B4: QUIMICA INDUSTRIAL | C4: N/A | D4: M.H | E4: IMPUESTOS | G4: 65.68 | H4: ADELAYDA | I4: AGRICOLA | J4: CARGOS A CLIENTES | K4: 45609 | L4: =IF(ISBLANK(K4),"",UPPER(TEXT(K4,"MMMM"))) -> NOVIEMBRE
A5: 008-2024 | B5: QUIMICA INDUSTRIAL | C5: N/A | D5: CEPA | E5: ALMACENAJE | G5: 25.99 | H5: ADELAYDA | I5: AGRICOLA | J5: CARGOS A CLIENTES | K5: 45609 | L5: =IF(ISBLANK(K5),"",UPPER(TEXT(K5,"MMMM"))) -> NOVIEMBRE | M5: TRUE | N5: Proteger registro
L6: =IF(ISBLANK(K6),"",UPPER(TEXT(K6,"MMMM")))
L7: =IF(ISBLANK(K7),"",UPPER(TEXT(K7,"MMMM")))
L8: =IF(ISBLANK(K8),"",UPPER(TEXT(K8,"MMMM")))
L9: =IF(ISBLANK(K9),"",UPPER(TEXT(K9,"MMMM")))
L10: =IF(ISBLANK(K10),"",UPPER(TEXT(K10,"MMMM")))
L11: =IF(ISBLANK(K11),"",UPPER(TEXT(K11,"MMMM")))
L12: =IF(ISBLANK(K12),"",UPPER(TEXT(K12,"MMMM")))
L13: =IF(ISBLANK(K13),"",UPPER(TEXT(K13,"MMMM")))
L14: =IF(ISBLANK(K14),"",UPPER(TEXT(K14,"MMMM")))
L15: =IF(ISBLANK(K15),"",UPPER(TEXT(K15,"MMMM")))
L16: =IF(ISBLANK(K16),"",UPPER(TEXT(K16,"MMMM")))
L17: =IF(ISBLANK(K17),"",UPPER(TEXT(K17,"MMMM")))
... L1001: =IF(ISBLANK(K1001),"",UPPER(TEXT(K1001,"MMMM")))

Sheet CALCULO COBROS
A1: CALCULO DE COBROS
A3: Número OS | D3: Cliente | G3: RESUMEN DE COBRO
D4: =IFERROR(VLOOKUP($A$4,'BASE OS'!A:B,2,FALSE),"") | G4: Total Servicios (IVA incluido) | H4: =SUM(F15:F24)+((SUM(F15:F24)*13%)) -> 0
G5: Gastos a Terceros: | H5: =SUM(E30:E39) -> 0
A6: Subcliente | D6: DUCA | G6: Total a pagar: | H6: =SUM(H4:H5) -> 0
A7: =IFERROR(VLOOKUP($A$4,'BASE OS'!A:C,3,FALSE),"") | D7: =IFERROR(VLOOKUP($A$4,'BASE OS'!A:D,4,FALSE),"")
A9: Referencia/BL | D9: Fecha
A10: =IFERROR(VLOOKUP($A$4,'BASE OS'!A:F,6,FALSE),"") | D10: =IFERROR(VLOOKUP($A$4,'BASE OS'!A:G,7,FALSE),"")
A13: SERVICIOS PRESTADOS
A14: SI / NO | B14: SERVICIO | D14: PRECIO BASE | E14: AJUSTE | F14: PRECIO FINAL | G14: NOTAS
D15: =IF(AND(LEN(B15)>0,LEN($D$4)>0),IFERROR(VLOOKUP(B15,TARIFARIO!$I$2:$J$10000,2,FALSE),"Servicio no encontrado"),"") | F15: =IFERROR(IF(AND(A15=TRUE,D15<>""),D15+IF(E15<>"",E15,0),""),"")
D16: =IF(AND(LEN(B16)>0,LEN($D$4)>0),IFERROR(VLOOKUP(B16,TARIFARIO!$I$2:$J$10000,2,FALSE),"Servicio no encontrado"),"") | F16: =IFERROR(IF(AND(A16=TRUE,D16<>""),D16+IF(E16<>"",E16,0),""),"")
D17: =IF(AND(LEN(B17)>0,LEN($D$4)>0),IFERROR(VLOOKUP(B17,TARIFARIO!$I$2:$J$10000,2,FALSE),"Servicio no encontrado"),"") | F17: =IFERROR(IF(AND(A17=TRUE,D17<>""),D17+IF(E17<>"",E17,0),""),"")
D18: =IF(AND(LEN(B18)>0,LEN($D$4)>0),IFERROR(VLOOKUP(B18,TARIFARIO!$I$2:$J$10000,2,FALSE),"Servicio no encontrado"),"") | F18: =IFERROR(IF(AND(A18=TRUE,D18<>""),D18+IF(E18<>"",E18,0),""),"")
D19: =IF(AND(LEN(B19)>0,LEN($D$4)>0),IFERROR(VLOOKUP(B19,TARIFARIO!$I$2:$J$10000,2,FALSE),"Servicio no encontrado"),"") | F19: =IFERROR(IF(AND(A19=TRUE,D19<>""),D19+IF(E19<>"",E19,0),""),"")
D20: =IF(AND(LEN(B20)>0,LEN($D$4)>0),IFERROR(VLOOKUP(B20,TARIFARIO!$I$2:$J$10000,2,FALSE),"Servicio no encontrado"),"") | F20: =IFERROR(IF(AND(A20=TRUE,D20<>""),D20+IF(E20<>"",E20,0),""),"")
D21: =IF(AND(LEN(B21)>0,LEN($D$4)>0),IFERROR(VLOOKUP(B21,TARIFARIO!$I$2:$J$10000,2,FALSE),"Servicio no encontrado"),"")
D22: =IF(AND(LEN(B22)>0,LEN($D$4)>0),IFERROR(VLOOKUP(B22,TARIFARIO!$I$2:$J$10000,2,FALSE),"Servicio no encontrado"),"")
D23: =IF(AND(LEN(B23)>0,LEN($D$4)>0),IFERROR(VLOOKUP(B23,TARIFARIO!$I$2:$J$10000,2,FALSE),"Servicio no encontrado"),"")
D24: =IF(AND(LEN(B24)>0,LEN($D$4)>0),IFERROR(VLOOKUP(B24,TARIFARIO!$I$2:$J$10000,2,FALSE),"Servicio no encontrado"),"") | F24: =IFERROR(IF(AND(A24=TRUE,D24<>""),D24+IF(E24<>"",E24,0),""),"")
A25: TOTALES | D25: =IF(SUM(D15:D24)=0,"",SUM(D15:D24)) | E25: =IF(SUM(E15:E24)=0,"",SUM(E15:E24)) | F25: =IF(SUM(F15:F24)=0,"",SUM(F15:F24))
A28: TRANSFERENCIAS ASOCIADAS
A29: =IFERROR(__xludf.DUMMYFUNCTION("QUERY('BASE TRANSFERENCIAS'!A:L,""SELECT I,D,E,F,G,H WHERE A= '""&$A$4&""' ORDER BY I DESC"",1)"),"#REF!") -> #REF!
A40: TOTALES | E40: =SUM(E30:E39) -> 0

Sheet HISTÓRICO COBROS
A1: HISTORICO DE COBROS
A2: OS | B2: FECHA | C2: CLIENTE | D2: SERVICIOS | E2: TOTAL SERVICIOS | F2: TOTAL GASTOS A TERCEROS | G2: TOTAL COBRADO | H2: NOTAS
A3: 001-2024 | B3: 45606 | C3: PANADERIA SINAI | D3: ASESORÍA Y GESTIÓN ADUANAL - OTRO | E3: 129.95 | F3: 33.284 | G3: 163.234
A4: 002-2024 | B4: 45606 | C4: PINTO Y COMPANIA | D4: ASESORÍA Y GESTIÓN ADUANAL - OTRO | E4: 67.8 | F4: 0 | G4: 67.8
A5: 003-2024 | B5: 45606 | C5: DIVACO | D5: ASESORIA Y GESTION ADUANERA - ACAJUTLA | E5: 79.1 | F5: 0 | G5: 79.1
A6: 004-2024 | B6: 45606 | C6: DIGICEL | D6: ASESORIA Y GESTION ADUANERA ALMACENADORA - AEROPUERTO, TRANSPORTE LOCAL DHL - DIGICEL | E6: 113 | F6: 0 | G6: 113
A7: 008-2024 | B7: 45609 | C7: QUIMICA INDUSTRIAL | D7: ASESORÍA Y GESTIÓN ADUANAL - OTRO, TRANSPORTE LOCAL - OTRO | E7: 209.05 | F7: 91.67 | G7: 300.72

Sheet CXC
A1: OS | B1: CLIENTE | C1: Fecha de Factura | D1: TIPO | E1: Numero | F1: Fecha de vencimiento | G1: Nº Quedan | H1: Facturacion | I1: Gastos a tercero | J1: Total de Facturación | K1: Abono o Pago Facturación | L1: Abono o Pago Prestamos | M1: CxC | N1: CXC Facturación | O1: CXC Prestamos | P1: Fecha de Abono | Q1: Tipo de pago | R1: Estado | S1: Días Vencidos | T1: DUCA | U1: PO | V1: Observaciones | W1: Mes | X1: No. Mes | Y1: Año
A2: 001-2024 | B2: =IF(A2="","",VLOOKUP(A2,'BASE OS'!$A$2:$I1000,2,FALSE)) -> PANADERIA SINAI | C2: 45608 | D2: DTE | H2: 129.95 | I2: 33.284 | J2: =H2+I2 -> 163.234 | M2: =J2-K2-L2 -> 163.234 | Q2: TRANSFERENCIA | R2: PENDIENTE | T2: =IF(A2="","",VLOOKUP(A2,'BASE OS'!$A$2:$I1000,4,FALSE)) -> 4-38493 | W2: =IF(ISBLANK(C2),"",UPPER(TEXT(C2,"MMMM"))) -> NOVIEMBRE | X2: =IF(C2="","",MONTH(C2)) -> 11 | Y2: =IF(C2="","", YEAR(C2)) -> 2024
A3: 002-2024 | B3: =IF(A3="","",VLOOKUP(A3,'BASE OS'!$A$2:$I1000,2,FALSE)) -> PINTO Y COMPANIA | C3: 45608 | D3: DTE | H3: 67.8 | I3: 0 | J3: =H3+I3 -> 67.8 | M3: =J3-K3-L3 -> 67.8 | Q3: TRANSFERENCIA | R3: PENDIENTE | T3: =IF(A3="","",VLOOKUP(A3,'BASE OS'!$A$2:$I1000,4,FALSE)) -> 4-28394 | W3: =IF(ISBLANK(C3),"",UPPER(TEXT(C3,"MMMM"))) -> NOVIEMBRE | X3: =IF(C3="","",MONTH(C3)) -> 11 | Y3: =IF(C3="","", YEAR(C3)) -> 2024
A4: 003-2024 | B4: =IF(A4="","",VLOOKUP(A4,'BASE OS'!$A$2:$I1000,2,FALSE)) -> DIVACO | C4: 45608 | D4: DTE | H4: 79.1 | I4: 0 | J4: =H4+I4 -> 79.1 | M4: =J4-K4-L4 -> 79.1 | Q4: TRANSFERENCIA | R4: PENDIENTE | T4: =IF(A4="","",VLOOKUP(A4,'BASE OS'!$A$2:$I1000,4,FALSE)) -> 4-23934 | W4: =IF(ISBLANK(C4),"",UPPER(TEXT(C4,"MMMM"))) -> NOVIEMBRE | X4: =IF(C4="","",MONTH(C4)) -> 11 | Y4: =IF(C4="","", YEAR(C4)) -> 2024
A5: 004-2024 | B5: =IF(A5="","",VLOOKUP(A5,'BASE OS'!$A$2:$I1000,2,FALSE)) -> DIGICEL | C5: 45609 | D5: DTE | H5: 113 | I5: 0 | J5: =H5+I5 -> 113 | M5: =J5-K5-L5 -> 113 | Q5: TRANSFERENCIA | R5: PENDIENTE | T5: =IF(A5="","",VLOOKUP(A5,'BASE OS'!$A$2:$I1000,4,FALSE)) -> 4-29394 | W5: =IF(ISBLANK(C5),"",UPPER(TEXT(C5,"MMMM"))) -> NOVIEMBRE | X5: =IF(C5="","",MONTH(C5)) -> 11 | Y5: =IF(C5="","", YEAR(C5)) -> 2024
A6: 005-2024 | B6: =IF(A6="","",VLOOKUP(A6,'BASE OS'!$A$2:$I1000,2,FALSE)) -> AISAL | C6: 45609 | D6: DTE | H6: 50.59 | I6: 53.55 | J6: =H6+I6 -> 104.14 | M6: =J6-K6-L6 -> 104.14 | Q6: TRANSFERENCIA | R6: PENDIENTE | T6: =IF(A6="","",VLOOKUP(A6,'BASE OS'!$A$2:$I1000,4,FALSE)) -> 4-22567 | W6: =IF(ISBLANK(C6),"",UPPER(TEXT(C6,"MMMM"))) -> NOVIEMBRE | X6: =IF(C6="","",MONTH(C6)) -> 11 | Y6: =IF(C6="","", YEAR(C6)) -> 2024
A7: 006-2024 | B7: =IF(A7="","",VLOOKUP(A7,'BASE OS'!$A$2:$I1000,2,FALSE)) -> GEVI | C7: 45609 | D7: DTE | H7: 25.1 | I7: 30.55 | J7: =H7+I7 -> 55.65 | M7: =J7-K7-L7 -> 55.65 | Q7: TRANSFERENCIA | R7: PENDIENTE | T7: =IF(A7="","",VLOOKUP(A7,'BASE OS'!$A$2:$I1000,4,FALSE)) -> 4-35685 | W7: =IF(ISBLANK(C7),"",UPPER(TEXT(C7,"MMMM"))) -> NOVIEMBRE | X7: =IF(C7="","",MONTH(C7)) -> 11 | Y7: =IF(C7="","", YEAR(C7)) -> 2024
A8: 007-2024 | B8: =IF(A8="","",VLOOKUP(A8,'BASE OS'!$A$2:$I1000,2,FALSE)) -> AISAL | C8: 45609 | D8: DTE | H8: 50.1 | I8: 0 | J8: =H8+I8 -> 50.1 | M8: =J8-K8-L8 -> 50.1 | Q8: TRANSFERENCIA | R8: PENDIENTE | T8: =IF(A8="","",VLOOKUP(A8,'BASE OS'!$A$2:$I1000,4,FALSE)) -> 4-35969 | W8: =IF(ISBLANK(C8),"",UPPER(TEXT(C8,"MMMM"))) -> NOVIEMBRE | X8: =IF(C8="","",MONTH(C8)) -> 11 | Y8: =IF(C8="","", YEAR(C8)) -> 2024
A9: 008-2024 | B9: =IF(A9="","",VLOOKUP(A9,'BASE OS'!$A$2:$I1000,2,FALSE)) -> QUIMICA INDUSTRIAL | C9: 45609 | D9: DTE | H9: 209.05 | I9: 91.67 | J9: =H9+I9 -> 300.72 | M9: =J9-K9-L9 -> 300.72 | Q9: TRANSFERENCIA | R9: PENDIENTE | T9: =IF(A9="","",VLOOKUP(A9,'BASE OS'!$A$2:$I1000,4,FALSE)) -> 4-38492 | W9: =IF(ISBLANK(C9),"",UPPER(TEXT(C9,"MMMM"))) -> NOVIEMBRE | X9: =IF(C9="","",MONTH(C9)) -> 11 | Y9: =IF(C9="","", YEAR(C9)) -> 2024
B10: =IF(A10="","",VLOOKUP(A10,'BASE OS'!$A$2:$I1000,2,FALSE)) | J10: =H10+I10 -> 0 | M10: =J10-K10-L10 -> 0 | T10: =IF(A10="","",VLOOKUP(A10,'BASE OS'!$A$2:$I1000,4,FALSE)) | W10: =IF(ISBLANK(C10),"",UPPER(TEXT(C10,"MMMM"))) | X10: =IF(C10="","",MONTH(C10)) | Y10: =IF(C10="","", YEAR(C10))
B11: =IF(A11="","",VLOOKUP(A11,'BASE OS'!$A$2:$I1000,2,FALSE)) | J11: =H11+I11 -> 0 | M11: =J11-K11-L11 -> 0 | T11: =IF(A11="","",VLOOKUP(A11,'BASE OS'!$A$2:$I1000,4,FALSE)) | W11: =IF(ISBLANK(C11),"",UPPER(TEXT(C11,"MMMM"))) | X11: =IF(C11="","",MONTH(C11)) | Y11: =IF(C11="","", YEAR(C11))
B12: =IF(A12="","",VLOOKUP(A12,'BASE OS'!$A$2:$I1000,2,FALSE)) | J12: =H12+I12 -> 0 | M12: =J12-K12-L12 -> 0 | T12: =IF(A12="","",VLOOKUP(A12,'BASE OS'!$A$2:$I1000,4,FALSE)) | W12: =IF(ISBLANK(C12),"",UPPER(TEXT(C12,"MMMM"))) | X12: =IF(C12="","",MONTH(C12)) | Y12: =IF(C12="","", YEAR(C12))
B13: =IF(A13="","",VLOOKUP(A13,'BASE OS'!$A$2:$I1000,2,FALSE)) | J13: =H13+I13 -> 0 | M13: =J13-K13-L13 -> 0 | T13: =IF(A13="","",VLOOKUP(A13,'BASE OS'!$A$2:$I1000,4,FALSE)) | W13: =IF(ISBLANK(C13),"",UPPER(TEXT(C13,"MMMM"))) | X13: =IF(C13="","",MONTH(C13)) | Y13: =IF(C13="","", YEAR(C13))
B14: =IF(A14="","",VLOOKUP(A14,'BASE OS'!$A$2:$I1000,2,FALSE)) | J14: =H14+I14 -> 0 | M14: =J14-K14-L14 -> 0 | T14: =IF(A14="","",VLOOKUP(A14,'BASE OS'!$A$2:$I1000,4,FALSE)) | W14: =IF(ISBLANK(C14),"",UPPER(TEXT(C14,"MMMM"))) | X14: =IF(C14="","",MONTH(C14)) | Y14: =IF(C14="","", YEAR(C14))
B15: =IF(A15="","",VLOOKUP(A15,'BASE OS'!$A$2:$I1000,2,FALSE)) | J15: =H15+I15 -> 0 | M15: =J15-K15-L15 -> 0 | T15: =IF(A15="","",VLOOKUP(A15,'BASE OS'!$A$2:$I1000,4,FALSE)) | W15: =IF(ISBLANK(C15),"",UPPER(TEXT(C15,"MMMM"))) | X15: =IF(C15="","",MONTH(C15)) | Y15: =IF(C15="","", YEAR(C15))
B16: =IF(A16="","",VLOOKUP(A16,'BASE OS'!$A$2:$I1000,2,FALSE)) | J16: =H16+I16 -> 0 | M16: =J16-K16-L16 -> 0 | T16: =IF(A16="","",VLOOKUP(A16,'BASE OS'!$A$2:$I1000,4,FALSE)) | W16: =IF(ISBLANK(C16),"",UPPER(TEXT(C16,"MMMM"))) | X16: =IF(C16="","",MONTH(C16)) | Y16: =IF(C16="","", YEAR(C16))
B17: =IF(A17="","",VLOOKUP(A17,'BASE OS'!$A$2:$I1000,2,FALSE)) | J17: =H17+I17 -> 0 | M17: =J17-K17-L17 -> 0 | T17: =IF(A17="","",VLOOKUP(A17,'BASE OS'!$A$2:$I1000,4,FALSE)) | W17: =IF(ISBLANK(C17),"",UPPER(TEXT(C17,"MMMM"))) | X17: =IF(C17="","",MONTH(C17)) | Y17: =IF(C17="","", YEAR(C17))
B18: =IF(A18="","",VLOOKUP(A18,'BASE OS'!$A$2:$I1000,2,FALSE)) | J18: =H18+I18 -> 0 | M18: =J18-K18-L18 -> 0 | T18: =IF(A18="","",VLOOKUP(A18,'BASE OS'!$A$2:$I1000,4,FALSE)) | W18: =IF(ISBLANK(C18),"",UPPER(TEXT(C18,"MMMM"))) | X18: =IF(C18="","",MONTH(C18)) | Y18: =IF(C18="","", YEAR(C18))
B19: =IF(A19="","",VLOOKUP(A19,'BASE OS'!$A$2:$I1000,2,FALSE)) | J19: =H19+I19 -> 0 | M19: =J19-K19-L19 -> 0 | T19: =IF(A19="","",VLOOKUP(A19,'BASE OS'!$A$2:$I1000,4,FALSE)) | W19: =IF(ISBLANK(C19),"",UPPER(TEXT(C19,"MMMM"))) | X19: =IF(C19="","",MONTH(C19)) | Y19: =IF(C19="","", YEAR(C19))
B20: =IF(A20="","",VLOOKUP(A20,'BASE OS'!$A$2:$I1000,2,FALSE)) | J20: =H20+I20 -> 0 | M20: =J20-K20-L20 -> 0 | T20: =IF(A20="","",VLOOKUP(A20,'BASE OS'!$A$2:$I1000,4,FALSE)) | W20: =IF(ISBLANK(C20),"",UPPER(TEXT(C20,"MMMM"))) | X20: =IF(C20="","",MONTH(C20)) | Y20: =IF(C20="","", YEAR(C20))
B21: =IF(A21="","",VLOOKUP(A21,'BASE OS'!$A$2:$I1000,2,FALSE)) | J21: =H21+I21 -> 0 | M21: =J21-K21-L21 -> 0 | T21: =IF(A21="","",VLOOKUP(A21,'BASE OS'!$A$2:$I1000,4,FALSE)) | W21: =IF(ISBLANK(C21),"",UPPER(TEXT(C21,"MMMM"))) | X21: =IF(C21="","",MONTH(C21)) | Y21: =IF(C21="","", YEAR(C21))
B22: =IF(A22="","",VLOOKUP(A22,'BASE OS'!$A$2:$I1000,2,FALSE)) | J22: =H22+I22 -> 0 | M22: =J22-K22-L22 -> 0 | T22: =IF(A22="","",VLOOKUP(A22,'BASE OS'!$A$2:$I1000,4,FALSE)) | W22: =IF(ISBLANK(C22),"",UPPER(TEXT(C22,"MMMM"))) | X22: =IF(C22="","",MONTH(C22)) | Y22: =IF(C22="","", YEAR(C22))
B23: =IF(A23="","",VLOOKUP(A23,'BASE OS'!$A$2:$I1000,2,FALSE)) | J23: =H23+I23 -> 0 | M23: =J23-K23-L23 -> 0 | T23: =IF(A23="","",VLOOKUP(A23,'BASE OS'!$A$2:$I1000,4,FALSE)) | W23: =IF(ISBLANK(C23),"",UPPER(TEXT(C23,"MMMM"))) | X23: =IF(C23="","",MONTH(C23)) | Y23: =IF(C23="","", YEAR(C23))
B24: =IF(A24="","",VLOOKUP(A24,'BASE OS'!$A$2:$I1000,2,FALSE)) | J24: =H24+I24 -> 0 | M24: =J24-K24-L24 -> 0 | T24: =IF(A24="","",VLOOKUP(A24,'BASE OS'!$A$2:$I1000,4,FALSE)) | W24: =IF(ISBLANK(C24),"",UPPER(TEXT(C24,"MMMM"))) | X24: =IF(C24="","",MONTH(C24)) | Y24: =IF(C24="","", YEAR(C24))
B25: =IF(A25="","",VLOOKUP(A25,'BASE OS'!$A$2:$I1000,2,FALSE)) | J25: =H25+I25 -> 0 | M25: =J25-K25-L25 -> 0 | T25: =IF(A25="","",VLOOKUP(A25,'BASE OS'!$A$2:$I1000,4,FALSE)) | W25: =IF(ISBLANK(C25),"",UPPER(TEXT(C25,"MMMM"))) | X25: =IF(C25="","",MONTH(C25)) | Y25: =IF(C25="","", YEAR(C25))
B26: =IF(A26="","",VLOOKUP(A26,'BASE OS'!$A$2:$I1000,2,FALSE)) | J26: =H26+I26 -> 0 | M26: =J26-K26-L26 -> 0 | T26: =IF(A26="","",VLOOKUP(A26,'BASE OS'!$A$2:$I1000,4,FALSE)) | W26: =IF(ISBLANK(C26),"",UPPER(TEXT(C26,"MMMM"))) | X26: =IF(C26="","",MONTH(C26)) | Y26: =IF(C26="","", YEAR(C26))
B27: =IF(A27="","",VLOOKUP(A27,'BASE OS'!$A$2:$I1000,2,FALSE)) | J27: =H27+I27 -> 0 | M27: =J27-K27-L27 -> 0 | T27: =IF(A27="","",VLOOKUP(A27,'BASE OS'!$A$2:$I1000,4,FALSE)) | W27: =IF(ISBLANK(C27),"",UPPER(TEXT(C27,"MMMM"))) | X27: =IF(C27="","",MONTH(C27)) | Y27: =IF(C27="","", YEAR(C27))
B28: =IF(A28="","",VLOOKUP(A28,'BASE OS'!$A$2:$I1000,2,FALSE)) | J28: =H28+I28 -> 0 | M28: =J28-K28-L28 -> 0 | T28: =IF(A28="","",VLOOKUP(A28,'BASE OS'!$A$2:$I1000,4,FALSE)) | W28: =IF(ISBLANK(C28),"",UPPER(TEXT(C28,"MMMM"))) | X28: =IF(C28="","",MONTH(C28)) | Y28: =IF(C28="","", YEAR(C28))
B29: =IF(A29="","",VLOOKUP(A29,'BASE OS'!$A$2:$I1000,2,FALSE)) | J29: =H29+I29 -> 0 | M29: =J29-K29-L29 -> 0 | T29: =IF(A29="","",VLOOKUP(A29,'BASE OS'!$A$2:$I1000,4,FALSE)) | W29: =IF(ISBLANK(C29),"",UPPER(TEXT(C29,"MMMM"))) | X29: =IF(C29="","",MONTH(C29)) | Y29: =IF(C29="","", YEAR(C29))
B30: =IF(A30="","",VLOOKUP(A30,'BASE OS'!$A$2:$I1000,2,FALSE)) | J30: =H30+I30 -> 0 | M30: =J30-K30-L30 -> 0 | T30: =IF(A30="","",VLOOKUP(A30,'BASE OS'!$A$2:$I1000,4,FALSE)) | W30: =IF(ISBLANK(C30),"",UPPER(TEXT(C30,"MMMM"))) | X30: =IF(C30="","",MONTH(C30)) | Y30: =IF(C30="","", YEAR(C30))
B31: =IF(A31="","",VLOOKUP(A31,'BASE OS'!$A$2:$I1000,2,FALSE)) | J31: =H31+I31 -> 0 | M31: =J31-K31-L31 -> 0 | T31: =IF(A31="","",VLOOKUP(A31,'BASE OS'!$A$2:$I1000,4,FALSE)) | W31: =IF(ISBLANK(C31),"",UPPER(TEXT(C31,"MMMM"))) | X31: =IF(C31="","",MONTH(C31)) | Y31: =IF(C31="","", YEAR(C31))
B32: =IF(A32="","",VLOOKUP(A32,'BASE OS'!$A$2:$I1000,2,FALSE)) | J32: =H32+I32 -> 0 | M32: =J32-K32-L32 -> 0 | T32: =IF(A32="","",VLOOKUP(A32,'BASE OS'!$A$2:$I1000,4,FALSE)) | W32: =IF(ISBLANK(C32),"",UPPER(TEXT(C32,"MMMM"))) | X32: =IF(C32="","",MONTH(C32)) | Y32: =IF(C32="","", YEAR(C32))
B33: =IF(A33="","",VLOOKUP(A33,'BASE OS'!$A$2:$I1000,2,FALSE)) | J33: =H33+I33 -> 0 | M33: =J33-K33-L33 -> 0 | T33: =IF(A33="","",VLOOKUP(A33,'BASE OS'!$A$2:$I1000,4,FALSE)) | W33: =IF(ISBLANK(C33),"",UPPER(TEXT(C33,"MMMM"))) | X33: =IF(C33="","",MONTH(C33)) | Y33: =IF(C33="","", YEAR(C33))
B34: =IF(A34="","",VLOOKUP(A34,'BASE OS'!$A$2:$I1000,2,FALSE)) | J34: =H34+I34 -> 0 | M34: =J34-K34-L34 -> 0 | T34: =IF(A34="","",VLOOKUP(A34,'BASE OS'!$A$2:$I1000,4,FALSE)) | W34: =IF(ISBLANK(C34),"",UPPER(TEXT(C34,"MMMM"))) | X34: =IF(C34="","",MONTH(C34)) | Y34: =IF(C34="","", YEAR(C34))
B35: =IF(A35="","",VLOOKUP(A35,'BASE OS'!$A$2:$I1000,2,FALSE)) | J35: =H35+I35 -> 0 | M35: =J35-K35-L35 -> 0 | T35: =IF(A35="","",VLOOKUP(A35,'BASE OS'!$A$2:$I1000,4,FALSE)) | W35: =IF(ISBLANK(C35),"",UPPER(TEXT(C35,"MMMM"))) | X35: =IF(C35="","",MONTH(C35)) | Y35: =IF(C35="","", YEAR(C35))
B36: =IF(A36="","",VLOOKUP(A36,'BASE OS'!$A$2:$I1000,2,FALSE)) | J36: =H36+I36 -> 0 | M36: =J36-K36-L36 -> 0 | T36: =IF(A36="","",VLOOKUP(A36,'BASE OS'!$A$2:$I1000,4,FALSE)) | W36: =IF(ISBLANK(C36),"",UPPER(TEXT(C36,"MMMM"))) | X36: =IF(C36="","",MONTH(C36)) | Y36: =IF(C36="","", YEAR(C36))
B37: =IF(A37="","",VLOOKUP(A37,'BASE OS'!$A$2:$I1000,2,FALSE)) | J37: =H37+I37 -> 0 | M37: =J37-K37-L37 -> 0 | T37: =IF(A37="","",VLOOKUP(A37,'BASE OS'!$A$2:$I1000,4,FALSE)) | W37: =IF(ISBLANK(C37),"",UPPER(TEXT(C37,"MMMM"))) | X37: =IF(C37="","",MONTH(C37)) | Y37: =IF(C37="","", YEAR(C37))
B38: =IF(A38="","",VLOOKUP(A38,'BASE OS'!$A$2:$I1000,2,FALSE)) | J38: =H38+I38 -> 0 | M38: =J38-K38-L38 -> 0 | T38: =IF(A38="","",VLOOKUP(A38,'BASE OS'!$A$2:$I1000,4,FALSE)) | W38: =IF(ISBLANK(C38),"",UPPER(TEXT(C38,"MMMM"))) | X38: =IF(C38="","",MONTH(C38)) | Y38: =IF(C38="","", YEAR(C38))
B39: =IF(A39="","",VLOOKUP(A39,'BASE OS'!$A$2:$I1000,2,FALSE)) | J39: =H39+I39 -> 0 | M39: =J39-K39-L39 -> 0 | T39: =IF(A39="","",VLOOKUP(A39,'BASE OS'!$A$2:$I1000,4,FALSE)) | W39: =IF(ISBLANK(C39),"",UPPER(TEXT(C39,"MMMM"))) | X39: =IF(C39="","",MONTH(C39)) | Y39: =IF(C39="","", YEAR(C39))
B40: =IF(A40="","",VLOOKUP(A40,'BASE OS'!$A$2:$I1000,2,FALSE)) | J40: =H40+I40 -> 0 | M40: =J40-K40-L40 -> 0 | T40: =IF(A40="","",VLOOKUP(A40,'BASE OS'!$A$2:$I1000,4,FALSE)) | W40: =IF(ISBLANK(C40),"",UPPER(TEXT(C40,"MMMM"))) | X40: =IF(C40="","",MONTH(C40)) | Y40: =IF(C40="","", YEAR(C40))
B41: =IF(A41="","",VLOOKUP(A41,'BASE OS'!$A$2:$I1000,2,FALSE)) | J41: =H41+I41 -> 0 | M41: =J41-K41-L41 -> 0 | T41: =IF(A41="","",VLOOKUP(A41,'BASE OS'!$A$2:$I1000,4,FALSE)) | W41: =IF(ISBLANK(C41),"",UPPER(TEXT(C41,"MMMM"))) | X41: =IF(C41="","",MONTH(C41)) | Y41: =IF(C41="","", YEAR(C41))
B42: =IF(A42="","",VLOOKUP(A42,'BASE OS'!$A$2:$I1000,2,FALSE)) | J42: =H42+I42 -> 0 | M42: =J42-K42-L42 -> 0 | T42: =IF(A42="","",VLOOKUP(A42,'BASE OS'!$A$2:$I1000,4,FALSE)) | W42: =IF(ISBLANK(C42),"",UPPER(TEXT(C42,"MMMM"))) | X42: =IF(C42="","",MONTH(C42)) | Y42: =IF(C42="","", YEAR(C42))
B43: =IF(A43="","",VLOOKUP(A43,'BASE OS'!$A$2:$I1000,2,FALSE)) | J43: =H43+I43 -> 0 | M43: =J43-K43-L43 -> 0 | T43: =IF(A43="","",VLOOKUP(A43,'BASE OS'!$A$2:$I1000,4,FALSE)) | W43: =IF(ISBLANK(C43),"",UPPER(TEXT(C43,"MMMM"))) | X43: =IF(C43="","",MONTH(C43)) | Y43: =IF(C43="","", YEAR(C43))
B44: =IF(A44="","",VLOOKUP(A44,'BASE OS'!$A$2:$I1000,2,FALSE)) | J44: =H44+I44 -> 0 | M44: =J44-K44-L44 -> 0 | T44: =IF(A44="","",VLOOKUP(A44,'BASE OS'!$A$2:$I1000,4,FALSE)) | W44: =IF(ISBLANK(C44),"",UPPER(TEXT(C44,"MMMM"))) | X44: =IF(C44="","",MONTH(C44)) | Y44: =IF(C44="","", YEAR(C44))
B45: =IF(A45="","",VLOOKUP(A45,'BASE OS'!$A$2:$I1000,2,FALSE)) | J45: =H45+I45 -> 0 | M45: =J45-K45-L45 -> 0 | T45: =IF(A45="","",VLOOKUP(A45,'BASE OS'!$A$2:$I1000,4,FALSE)) | W45: =IF(ISBLANK(C45),"",UPPER(TEXT(C45,"MMMM"))) | X45: =IF(C45="","",MONTH(C45)) | Y45: =IF(C45="","", YEAR(C45))
B46: =IF(A46="","",VLOOKUP(A46,'BASE OS'!$A$2:$I1000,2,FALSE)) | J46: =H46+I46 -> 0 | M46: =J46-K46-L46 -> 0 | T46: =IF(A46="","",VLOOKUP(A46,'BASE OS'!$A$2:$I1000,4,FALSE)) | W46: =IF(ISBLANK(C46),"",UPPER(TEXT(C46,"MMMM"))) | X46: =IF(C46="","",MONTH(C46)) | Y46: =IF(C46="","", YEAR(C46))
B47: =IF(A47="","",VLOOKUP(A47,'BASE OS'!$A$2:$I1000,2,FALSE)) | J47: =H47+I47 -> 0 | M47: =J47-K47-L47 -> 0 | T47: =IF(A47="","",VLOOKUP(A47,'BASE OS'!$A$2:$I1000,4,FALSE)) | W47: =IF(ISBLANK(C47),"",UPPER(TEXT(C47,"MMMM"))) | X47: =IF(C47="","",MONTH(C47)) | Y47: =IF(C47="","", YEAR(C47))
B48: =IF(A48="","",VLOOKUP(A48,'BASE OS'!$A$2:$I1000,2,FALSE)) | J48: =H48+I48 -> 0 | M48: =J48-K48-L48 -> 0 | T48: =IF(A48="","",VLOOKUP(A48,'BASE OS'!$A$2:$I1000,4,FALSE)) | W48: =IF(ISBLANK(C48),"",UPPER(TEXT(C48,"MMMM"))) | X48: =IF(C48="","",MONTH(C48)) | Y48: =IF(C48="","", YEAR(C48))
B49: =IF(A49="","",VLOOKUP(A49,'BASE OS'!$A$2:$I1000,2,FALSE)) | J49: =H49+I49 -> 0 | M49: =J49-K49-L49 -> 0 | T49: =IF(A49="","",VLOOKUP(A49,'BASE OS'!$A$2:$I1000,4,FALSE)) | W49: =IF(ISBLANK(C49),"",UPPER(TEXT(C49,"MMMM"))) | X49: =IF(C49="","",MONTH(C49)) | Y49: =IF(C49="","", YEAR(C49))
B50: =IF(A50="","",VLOOKUP(A50,'BASE OS'!$A$2:$I1000,2,FALSE)) | J50: =H50+I50 -> 0 | M50: =J50-K50-L50 -> 0 | T50: =IF(A50="","",VLOOKUP(A50,'BASE OS'!$A$2:$I1000,4,FALSE)) | W50: =IF(ISBLANK(C50),"",UPPER(TEXT(C50,"MMMM"))) | X50: =IF(C50="","",MONTH(C50)) | Y50: =IF(C50="","", YEAR(C50))
B51: =IF(A51="","",VLOOKUP(A51,'BASE OS'!$A$2:$I1000,2,FALSE)) | J51: =H51+I51 -> 0 | M51: =J51-K51-L51 -> 0 | T51: =IF(A51="","",VLOOKUP(A51,'BASE OS'!$A$2:$I1000,4,FALSE)) | W51: =IF(ISBLANK(C51),"",UPPER(TEXT(C51,"MMMM"))) | X51: =IF(C51="","",MONTH(C51)) | Y51: =IF(C51="","", YEAR(C51))
B52: =IF(A52="","",VLOOKUP(A52,'BASE OS'!$A$2:$I1000,2,FALSE)) | J52: =H52+I52 -> 0 | M52: =J52-K52-L52 -> 0 | T52: =IF(A52="","",VLOOKUP(A52,'BASE OS'!$A$2:$I1000,4,FALSE)) | W52: =IF(ISBLANK(C52),"",UPPER(TEXT(C52,"MMMM"))) | X52: =IF(C52="","",MONTH(C52)) | Y52: =IF(C52="","", YEAR(C52))
B53: =IF(A53="","",VLOOKUP(A53,'BASE OS'!$A$2:$I1000,2,FALSE)) | J53: =H53+I53 -> 0 | M53: =J53-K53-L53 -> 0 | T53: =IF(A53="","",VLOOKUP(A53,'BASE OS'!$A$2:$I1000,4,FALSE)) | W53: =IF(ISBLANK(C53),"",UPPER(TEXT(C53,"MMMM"))) | X53: =IF(C53="","",MONTH(C53)) | Y53: =IF(C53="","", YEAR(C53))
B54: =IF(A54="","",VLOOKUP(A54,'BASE OS'!$A$2:$I1000,2,FALSE)) | J54: =H54+I54 -> 0 | M54: =J54-K54-L54 -> 0 | T54: =IF(A54="","",VLOOKUP(A54,'BASE OS'!$A$2:$I1000,4,FALSE)) | W54: =IF(ISBLANK(C54),"",UPPER(TEXT(C54,"MMMM"))) | X54: =IF(C54="","",MONTH(C54)) | Y54: =IF(C54="","", YEAR(C54))
B55: =IF(A55="","",VLOOKUP(A55,'BASE OS'!$A$2:$I1000,2,FALSE)) | J55: =H55+I55 -> 0 | M55: =J55-K55-L55 -> 0 | T55: =IF(A55="","",VLOOKUP(A55,'BASE OS'!$A$2:$I1000,4,FALSE)) | W55: =IF(ISBLANK(C55),"",UPPER(TEXT(C55,"MMMM"))) | X55: =IF(C55="","",MONTH(C55)) | Y55: =IF(C55="","", YEAR(C55))
B56: =IF(A56="","",VLOOKUP(A56,'BASE OS'!$A$2:$I1000,2,FALSE)) | J56: =H56+I56 -> 0 | M56: =J56-K56-L56 -> 0 | T56: =IF(A56="","",VLOOKUP(A56,'BASE OS'!$A$2:$I1000,4,FALSE)) | W56: =IF(ISBLANK(C56),"",UPPER(TEXT(C56,"MMMM"))) | X56: =IF(C56="","",MONTH(C56)) | Y56: =IF(C56="","", YEAR(C56))
B57: =IF(A57="","",VLOOKUP(A57,'BASE OS'!$A$2:$I1000,2,FALSE)) | J57: =H57+I57 -> 0 | M57: =J57-K57-L57 -> 0 | T57: =IF(A57="","",VLOOKUP(A57,'BASE OS'!$A$2:$I1000,4,FALSE)) | W57: =IF(ISBLANK(C57),"",UPPER(TEXT(C57,"MMMM"))) | X57: =IF(C57="","",MONTH(C57)) | Y57: =IF(C57="","", YEAR(C57))
B58: =IF(A58="","",VLOOKUP(A58,'BASE OS'!$A$2:$I1000,2,FALSE)) | J58: =H58+I58 -> 0 | M58: =J58-K58-L58 -> 0 | T58: =IF(A58="","",VLOOKUP(A58,'BASE OS'!$A$2:$I1000,4,FALSE)) | W58: =IF(ISBLANK(C58),"",UPPER(TEXT(C58,"MMMM"))) | X58: =IF(C58="","",MONTH(C58)) | Y58: =IF(C58="","", YEAR(C58))
B59: =IF(A59="","",VLOOKUP(A59,'BASE OS'!$A$2:$I1000,2,FALSE)) | J59: =H59+I59 -> 0 | M59: =J59-K59-L59 -> 0 | T59: =IF(A59="","",VLOOKUP(A59,'BASE OS'!$A$2:$I1000,4,FALSE)) | W59: =IF(ISBLANK(C59),"",UPPER(TEXT(C59,"MMMM"))) | X59: =IF(C59="","",MONTH(C59)) | Y59: =IF(C59="","", YEAR(C59))
B60: =IF(A60="","",VLOOKUP(A60,'BASE OS'!$A$2:$I1000,2,FALSE)) | J60: =H60+I60 -> 0 | M60: =J60-K60-L60 -> 0 | T60: =IF(A60="","",VLOOKUP(A60,'BASE OS'!$A$2:$I1000,4,FALSE)) | W60: =IF(ISBLANK(C60),"",UPPER(TEXT(C60,"MMMM"))) | X60: =IF(C60="","",MONTH(C60)) | Y60: =IF(C60="","", YEAR(C60))
B61: =IF(A61="","",VLOOKUP(A61,'BASE OS'!$A$2:$I1000,2,FALSE)) | J61: =H61+I61 -> 0 | M61: =J61-K61-L61 -> 0 | T61: =IF(A61="","",VLOOKUP(A61,'BASE OS'!$A$2:$I1000,4,FALSE)) | W61: =IF(ISBLANK(C61),"",UPPER(TEXT(C61,"MMMM"))) | X61: =IF(C61="","",MONTH(C61)) | Y61: =IF(C61="","", YEAR(C61))
B62: =IF(A62="","",VLOOKUP(A62,'BASE OS'!$A$2:$I1000,2,FALSE)) | J62: =H62+I62 -> 0 | M62: =J62-K62-L62 -> 0 | T62: =IF(A62="","",VLOOKUP(A62,'BASE OS'!$A$2:$I1000,4,FALSE)) | W62: =IF(ISBLANK(C62),"",UPPER(TEXT(C62,"MMMM"))) | X62: =IF(C62="","",MONTH(C62)) | Y62: =IF(C62="","", YEAR(C62))
B63: =IF(A63="","",VLOOKUP(A63,'BASE OS'!$A$2:$I1000,2,FALSE)) | J63: =H63+I63 -> 0 | M63: =J63-K63-L63 -> 0 | T63: =IF(A63="","",VLOOKUP(A63,'BASE OS'!$A$2:$I1000,4,FALSE)) | W63: =IF(ISBLANK(C63),"",UPPER(TEXT(C63,"MMMM"))) | X63: =IF(C63="","",MONTH(C63)) | Y63: =IF(C63="","", YEAR(C63))
B64: =IF(A64="","",VLOOKUP(A64,'BASE OS'!$A$2:$I1000,2,FALSE)) | J64: =H64+I64 -> 0 | M64: =J64-K64-L64 -> 0 | T64: =IF(A64="","",VLOOKUP(A64,'BASE OS'!$A$2:$I1000,4,FALSE)) | W64: =IF(ISBLANK(C64),"",UPPER(TEXT(C64,"MMMM"))) | X64: =IF(C64="","",MONTH(C64)) | Y64: =IF(C64="","", YEAR(C64))
B65: =IF(A65="","",VLOOKUP(A65,'BASE OS'!$A$2:$I1000,2,FALSE)) | J65: =H65+I65 -> 0 | M65: =J65-K65-L65 -> 0 | T65: =IF(A65="","",VLOOKUP(A65,'BASE OS'!$A$2:$I1000,4,FALSE)) | W65: =IF(ISBLANK(C65),"",UPPER(TEXT(C65,"MMMM"))) | X65: =IF(C65="","",MONTH(C65)) | Y65: =IF(C65="","", YEAR(C65))
B66: =IF(A66="","",VLOOKUP(A66,'BASE OS'!$A$2:$I1000,2,FALSE)) | J66: =H66+I66 -> 0 | M66: =J66-K66-L66 -> 0 | T66: =IF(A66="","",VLOOKUP(A66,'BASE OS'!$A$2:$I1000,4,FALSE)) | W66: =IF(ISBLANK(C66),"",UPPER(TEXT(C66,"MMMM"))) | X66: =IF(C66="","",MONTH(C66)) | Y66: =IF(C66="","", YEAR(C66))
B67: =IF(A67="","",VLOOKUP(A67,'BASE OS'!$A$2:$I1000,2,FALSE)) | J67: =H67+I67 -> 0 | M67: =J67-K67-L67 -> 0 | T67: =IF(A67="","",VLOOKUP(A67,'BASE OS'!$A$2:$I1000,4,FALSE)) | W67: =IF(ISBLANK(C67),"",UPPER(TEXT(C67,"MMMM"))) | X67: =IF(C67="","",MONTH(C67)) | Y67: =IF(C67="","", YEAR(C67))
B68: =IF(A68="","",VLOOKUP(A68,'BASE OS'!$A$2:$I1000,2,FALSE)) | J68: =H68+I68 -> 0 | M68: =J68-K68-L68 -> 0 | T68: =IF(A68="","",VLOOKUP(A68,'BASE OS'!$A$2:$I1000,4,FALSE)) | W68: =IF(ISBLANK(C68),"",UPPER(TEXT(C68,"MMMM"))) | X68: =IF(C68="","",MONTH(C68)) | Y68: =IF(C68="","", YEAR(C68))
B69: =IF(A69="","",VLOOKUP(A69,'BASE OS'!$A$2:$I1000,2,FALSE)) | J69: =H69+I69 -> 0 | M69: =J69-K69-L69 -> 0 | T69: =IF(A69="","",VLOOKUP(A69,'BASE OS'!$A$2:$I1000,4,FALSE)) | W69: =IF(ISBLANK(C69),"",UPPER(TEXT(C69,"MMMM"))) | X69: =IF(C69="","",MONTH(C69)) | Y69: =IF(C69="","", YEAR(C69))
B70: =IF(A70="","",VLOOKUP(A70,'BASE OS'!$A$2:$I1000,2,FALSE)) | J70: =H70+I70 -> 0 | M70: =J70-K70-L70 -> 0 | T70: =IF(A70="","",VLOOKUP(A70,'BASE OS'!$A$2:$I1000,4,FALSE)) | W70: =IF(ISBLANK(C70),"",UPPER(TEXT(C70,"MMMM"))) | X70: =IF(C70="","",MONTH(C70)) | Y70: =IF(C70="","", YEAR(C70))
B71: =IF(A71="","",VLOOKUP(A71,'BASE OS'!$A$2:$I1000,2,FALSE)) | J71: =H71+I71 -> 0 | M71: =J71-K71-L71 -> 0 | T71: =IF(A71="","",VLOOKUP(A71,'BASE OS'!$A$2:$I1000,4,FALSE)) | W71: =IF(ISBLANK(C71),"",UPPER(TEXT(C71,"MMMM"))) | X71: =IF(C71="","",MONTH(C71)) | Y71: =IF(C71="","", YEAR(C71))
B72: =IF(A72="","",VLOOKUP(A72,'BASE OS'!$A$2:$I1000,2,FALSE)) | J72: =H72+I72 -> 0 | M72: =J72-K72-L72 -> 0 | T72: =IF(A72="","",VLOOKUP(A72,'BASE OS'!$A$2:$I1000,4,FALSE)) | W72: =IF(ISBLANK(C72),"",UPPER(TEXT(C72,"MMMM"))) | X72: =IF(C72="","",MONTH(C72)) | Y72: =IF(C72="","", YEAR(C72))
B73: =IF(A73="","",VLOOKUP(A73,'BASE OS'!$A$2:$I1000,2,FALSE)) | J73: =H73+I73 -> 0 | M73: =J73-K73-L73 -> 0 | T73: =IF(A73="","",VLOOKUP(A73,'BASE OS'!$A$2:$I1000,4,FALSE)) | W73: =IF(ISBLANK(C73),"",UPPER(TEXT(C73,"MMMM"))) | X73: =IF(C73="","",MONTH(C73)) | Y73: =IF(C73="","", YEAR(C73))
B74: =IF(A74="","",VLOOKUP(A74,'BASE OS'!$A$2:$I1000,2,FALSE)) | J74: =H74+I74 -> 0 | M74: =J74-K74-L74 -> 0 | T74: =IF(A74="","",VLOOKUP(A74,'BASE OS'!$A$2:$I1000,4,FALSE)) | W74: =IF(ISBLANK(C74),"",UPPER(TEXT(C74,"MMMM"))) | X74: =IF(C74="","",MONTH(C74)) | Y74: =IF(C74="","", YEAR(C74))
B75: =IF(A75="","",VLOOKUP(A75,'BASE OS'!$A$2:$I1000,2,FALSE)) | J75: =H75+I75 -> 0 | M75: =J75-K75-L75 -> 0 | T75: =IF(A75="","",VLOOKUP(A75,'BASE OS'!$A$2:$I1000,4,FALSE)) | W75: =IF(ISBLANK(C75),"",UPPER(TEXT(C75,"MMMM"))) | X75: =IF(C75="","",MONTH(C75)) | Y75: =IF(C75="","", YEAR(C75))
B76: =IF(A76="","",VLOOKUP(A76,'BASE OS'!$A$2:$I1000,2,FALSE)) | J76: =H76+I76 -> 0 | M76: =J76-K76-L76 -> 0 | T76: =IF(A76="","",VLOOKUP(A76,'BASE OS'!$A$2:$I1000,4,FALSE)) | W76: =IF(ISBLANK(C76),"",UPPER(TEXT(C76,"MMMM"))) | X76: =IF(C76="","",MONTH(C76)) | Y76: =IF(C76="","", YEAR(C76))
B77: =IF(A77="","",VLOOKUP(A77,'BASE OS'!$A$2:$I1000,2,FALSE)) | J77: =H77+I77 -> 0 | M77: =J77-K77-L77 -> 0 | T77: =IF(A77="","",VLOOKUP(A77,'BASE OS'!$A$2:$I1000,4,FALSE)) | W77: =IF(ISBLANK(C77),"",UPPER(TEXT(C77,"MMMM"))) | X77: =IF(C77="","",MONTH(C77)) | Y77: =IF(C77="","", YEAR(C77))
B78: =IF(A78="","",VLOOKUP(A78,'BASE OS'!$A$2:$I1000,2,FALSE)) | J78: =H78+I78 -> 0 | M78: =J78-K78-L78 -> 0 | T78: =IF(A78="","",VLOOKUP(A78,'BASE OS'!$A$2:$I1000,4,FALSE)) | W78: =IF(ISBLANK(C78),"",UPPER(TEXT(C78,"MMMM"))) | X78: =IF(C78="","",MONTH(C78)) | Y78: =IF(C78="","", YEAR(C78))
B79: =IF(A79="","",VLOOKUP(A79,'BASE OS'!$A$2:$I1000,2,FALSE)) | J79: =H79+I79 -> 0 | M79: =J79-K79-L79 -> 0 | T79: =IF(A79="","",VLOOKUP(A79,'BASE OS'!$A$2:$I1000,4,FALSE)) | W79: =IF(ISBLANK(C79),"",UPPER(TEXT(C79,"MMMM"))) | X79: =IF(C79="","",MONTH(C79)) | Y79: =IF(C79="","", YEAR(C79))
B80: =IF(A80="","",VLOOKUP(A80,'BASE OS'!$A$2:$I1000,2,FALSE)) | J80: =H80+I80 -> 0 | M80: =J80-K80-L80 -> 0 | T80: =IF(A80="","",VLOOKUP(A80,'BASE OS'!$A$2:$I1000,4,FALSE)) | W80: =IF(ISBLANK(C80),"",UPPER(TEXT(C80,"MMMM"))) | X80: =IF(C80="","",MONTH(C80)) | Y80: =IF(C80="","", YEAR(C80))
B81: =IF(A81="","",VLOOKUP(A81,'BASE OS'!$A$2:$I1000,2,FALSE)) | J81: =H81+I81 -> 0 | M81: =J81-K81-L81 -> 0 | T81: =IF(A81="","",VLOOKUP(A81,'BASE OS'!$A$2:$I1000,4,FALSE)) | W81: =IF(ISBLANK(C81),"",UPPER(TEXT(C81,"MMMM"))) | X81: =IF(C81="","",MONTH(C81)) | Y81: =IF(C81="","", YEAR(C81))
B82: =IF(A82="","",VLOOKUP(A82,'BASE OS'!$A$2:$I1000,2,FALSE)) | J82: =H82+I82 -> 0 | M82: =J82-K82-L82 -> 0 | T82: =IF(A82="","",VLOOKUP(A82,'BASE OS'!$A$2:$I1000,4,FALSE)) | W82: =IF(ISBLANK(C82),"",UPPER(TEXT(C82,"MMMM"))) | X82: =IF(C82="","",MONTH(C82)) | Y82: =IF(C82="","", YEAR(C82))
B83: =IF(A83="","",VLOOKUP(A83,'BASE OS'!$A$2:$I1000,2,FALSE)) | J83: =H83+I83 -> 0 | M83: =J83-K83-L83 -> 0 | T83: =IF(A83="","",VLOOKUP(A83,'BASE OS'!$A$2:$I1000,4,FALSE)) | W83: =IF(ISBLANK(C83),"",UPPER(TEXT(C83,"MMMM"))) | X83: =IF(C83="","",MONTH(C83)) | Y83: =IF(C83="","", YEAR(C83))
B84: =IF(A84="","",VLOOKUP(A84,'BASE OS'!$A$2:$I1000,2,FALSE)) | J84: =H84+I84 -> 0 | M84: =J84-K84-L84 -> 0 | T84: =IF(A84="","",VLOOKUP(A84,'BASE OS'!$A$2:$I1000,4,FALSE)) | W84: =IF(ISBLANK(C84),"",UPPER(TEXT(C84,"MMMM"))) | X84: =IF(C84="","",MONTH(C84)) | Y84: =IF(C84="","", YEAR(C84))
B85: =IF(A85="","",VLOOKUP(A85,'BASE OS'!$A$2:$I1000,2,FALSE)) | J85: =H85+I85 -> 0 | M85: =J85-K85-L85 -> 0 | T85: =IF(A85="","",VLOOKUP(A85,'BASE OS'!$A$2:$I1000,4,FALSE)) | W85: =IF(ISBLANK(C85),"",UPPER(TEXT(C85,"MMMM"))) | X85: =IF(C85="","",MONTH(C85)) | Y85: =IF(C85="","", YEAR(C85))
B86: =IF(A86="","",VLOOKUP(A86,'BASE OS'!$A$2:$I1000,2,FALSE)) | J86: =H86+I86 -> 0 | M86: =J86-K86-L86 -> 0 | T86: =IF(A86="","",VLOOKUP(A86,'BASE OS'!$A$2:$I1000,4,FALSE)) | W86: =IF(ISBLANK(C86),"",UPPER(TEXT(C86,"MMMM"))) | X86: =IF(C86="","",MONTH(C86)) | Y86: =IF(C86="","", YEAR(C86))
B87: =IF(A87="","",VLOOKUP(A87,'BASE OS'!$A$2:$I1000,2,FALSE)) | J87: =H87+I87 -> 0 | M87: =J87-K87-L87 -> 0 | T87: =IF(A87="","",VLOOKUP(A87,'BASE OS'!$A$2:$I1000,4,FALSE)) | W87: =IF(ISBLANK(C87),"",UPPER(TEXT(C87,"MMMM"))) | X87: =IF(C87="","",MONTH(C87)) | Y87: =IF(C87="","", YEAR(C87))
B88: =IF(A88="","",VLOOKUP(A88,'BASE OS'!$A$2:$I1000,2,FALSE)) | J88: =H88+I88 -> 0 | M88: =J88-K88-L88 -> 0 | T88: =IF(A88="","",VLOOKUP(A88,'BASE OS'!$A$2:$I1000,4,FALSE)) | W88: =IF(ISBLANK(C88),"",UPPER(TEXT(C88,"MMMM"))) | X88: =IF(C88="","",MONTH(C88)) | Y88: =IF(C88="","", YEAR(C88))
B89: =IF(A89="","",VLOOKUP(A89,'BASE OS'!$A$2:$I1000,2,FALSE)) | J89: =H89+I89 -> 0 | M89: =J89-K89-L89 -> 0 | T89: =IF(A89="","",VLOOKUP(A89,'BASE OS'!$A$2:$I1000,4,FALSE)) | W89: =IF(ISBLANK(C89),"",UPPER(TEXT(C89,"MMMM"))) | X89: =IF(C89="","",MONTH(C89)) | Y89: =IF(C89="","", YEAR(C89))
B90: =IF(A90="","",VLOOKUP(A90,'BASE OS'!$A$2:$I1000,2,FALSE)) | J90: =H90+I90 -> 0 | M90: =J90-K90-L90 -> 0 | T90: =IF(A90="","",VLOOKUP(A90,'BASE OS'!$A$2:$I1000,4,FALSE)) | W90: =IF(ISBLANK(C90),"",UPPER(TEXT(C90,"MMMM"))) | X90: =IF(C90="","",MONTH(C90)) | Y90: =IF(C90="","", YEAR(C90))
B91: =IF(A91="","",VLOOKUP(A91,'BASE OS'!$A$2:$I1000,2,FALSE)) | J91: =H91+I91 -> 0 | M91: =J91-K91-L91 -> 0 | T91: =IF(A91="","",VLOOKUP(A91,'BASE OS'!$A$2:$I1000,4,FALSE)) | W91: =IF(ISBLANK(C91),"",UPPER(TEXT(C91,"MMMM"))) | X91: =IF(C91="","",MONTH(C91)) | Y91: =IF(C91="","", YEAR(C91))
B92: =IF(A92="","",VLOOKUP(A92,'BASE OS'!$A$2:$I1000,2,FALSE)) | J92: =H92+I92 -> 0 | M92: =J92-K92-L92 -> 0 | T92: =IF(A92="","",VLOOKUP(A92,'BASE OS'!$A$2:$I1000,4,FALSE)) | W92: =IF(ISBLANK(C92),"",UPPER(TEXT(C92,"MMMM"))) | X92: =IF(C92="","",MONTH(C92)) | Y92: =IF(C92="","", YEAR(C92))
B93: =IF(A93="","",VLOOKUP(A93,'BASE OS'!$A$2:$I1000,2,FALSE)) | J93: =H93+I93 -> 0 | M93: =J93-K93-L93 -> 0 | T93: =IF(A93="","",VLOOKUP(A93,'BASE OS'!$A$2:$I1000,4,FALSE)) | W93: =IF(ISBLANK(C93),"",UPPER(TEXT(C93,"MMMM"))) | X93: =IF(C93="","",MONTH(C93)) | Y93: =IF(C93="","", YEAR(C93))
B94: =IF(A94="","",VLOOKUP(A94,'BASE OS'!$A$2:$I1000,2,FALSE)) | J94: =H94+I94 -> 0 | M94: =J94-K94-L94 -> 0 | T94: =IF(A94="","",VLOOKUP(A94,'BASE OS'!$A$2:$I1000,4,FALSE)) | W94: =IF(ISBLANK(C94),"",UPPER(TEXT(C94,"MMMM"))) | X94: =IF(C94="","",MONTH(C94)) | Y94: =IF(C94="","", YEAR(C94))
B95: =IF(A95="","",VLOOKUP(A95,'BASE OS'!$A$2:$I1000,2,FALSE)) | J95: =H95+I95 -> 0 | M95: =J95-K95-L95 -> 0 | T95: =IF(A95="","",VLOOKUP(A95,'BASE OS'!$A$2:$I1000,4,FALSE)) | W95: =IF(ISBLANK(C95),"",UPPER(TEXT(C95,"MMMM"))) | X95: =IF(C95="","",MONTH(C95)) | Y95: =IF(C95="","", YEAR(C95))
B96: =IF(A96="","",VLOOKUP(A96,'BASE OS'!$A$2:$I1000,2,FALSE)) | J96: =H96+I96 -> 0 | M96: =J96-K96-L96 -> 0 | T96: =IF(A96="","",VLOOKUP(A96,'BASE OS'!$A$2:$I1000,4,FALSE)) | W96: =IF(ISBLANK(C96),"",UPPER(TEXT(C96,"MMMM"))) | X96: =IF(C96="","",MONTH(C96)) | Y96: =IF(C96="","", YEAR(C96))
B97: =IF(A97="","",VLOOKUP(A97,'BASE OS'!$A$2:$I1000,2,FALSE)) | J97: =H97+I97 -> 0 | M97: =J97-K97-L97 -> 0 | T97: =IF(A97="","",VLOOKUP(A97,'BASE OS'!$A$2:$I1000,4,FALSE)) | W97: =IF(ISBLANK(C97),"",UPPER(TEXT(C97,"MMMM"))) | X97: =IF(C97="","",MONTH(C97)) | Y97: =IF(C97="","", YEAR(C97))
B98: =IF(A98="","",VLOOKUP(A98,'BASE OS'!$A$2:$I1000,2,FALSE)) | J98: =H98+I98 -> 0 | M98: =J98-K98-L98 -> 0 | T98: =IF(A98="","",VLOOKUP(A98,'BASE OS'!$A$2:$I1000,4,FALSE)) | W98: =IF(ISBLANK(C98),"",UPPER(TEXT(C98,"MMMM"))) | X98: =IF(C98="","",MONTH(C98)) | Y98: =IF(C98="","", YEAR(C98))
B99: =IF(A99="","",VLOOKUP(A99,'BASE OS'!$A$2:$I1000,2,FALSE)) | J99: =H99+I99 -> 0 | M99: =J99-K99-L99 -> 0 | T99: =IF(A99="","",VLOOKUP(A99,'BASE OS'!$A$2:$I1000,4,FALSE)) | W99: =IF(ISBLANK(C99),"",UPPER(TEXT(C99,"MMMM"))) | X99: =IF(C99="","",MONTH(C99)) | Y99: =IF(C99="","", YEAR(C99))
B100: =IF(A100="","",VLOOKUP(A100,'BASE OS'!$A$2:$I1000,2,FALSE)) | J100: =H100+I100 -> 0 | M100: =J100-K100-L100 -> 0 | T100: =IF(A100="","",VLOOKUP(A100,'BASE OS'!$A$2:$I1000,4,FALSE)) | W100: =IF(ISBLANK(C100),"",UPPER(TEXT(C100,"MMMM"))) | X100: =IF(C100="","",MONTH(C100)) | Y100: =IF(C100="","", YEAR(C100))
...

Sheet DATOS_COMPARACION
A1: OS | B1: CLIENTE | C1: FECHA | D1: SERVICIOS CXC | E1: SERVICIOS PREVISTO | F1: GASTOS A TERCEROS CXC | G1: GASTOS A TERCEROS PREVISTO | H1: TOTAL CXC | I1: TOTAL PREVISTO | J1: DIFERENCIA SERVICIOS | K1: DIFERENCIA GASTOS A TERCEROS
A2: {=UNIQUE(INDIRECT("CXC!A2:A"&COUNTA(CXC!A:A)))} -> 001-2024 | B2: {=IF(A2="","",VLOOKUP(A2,INDIRECT("CXC!A2:B"&COUNTA(CXC!A:A)),2,FALSE))} -> PANADERIA SINAI | C2: {=IF(A2="","",VLOOKUP(A2,INDIRECT("CXC!A2:C"&COUNTA(CXC!A:A)),3,FALSE))} -> 45608 | D2: {=IF(A2="","",VLOOKUP(A2,INDIRECT("CXC!A2:H"&COUNTA(CXC!A:A)),8,FALSE))} -> 129.95 | E2: {=IFERROR(IF(A2="","",VLOOKUP(A2,INDIRECT("HISTÓRICO COBROS!A3:E"&COUNTA('HISTÓRICO COBROS'!A:A)),5,FALSE)),"")} -> 129.95 | F2: {=IF(A2="","",VLOOKUP(A2,INDIRECT("CXC!A2:I"&COUNTA(CXC!A:A)),9,FALSE))} -> 33.284 | G2: {=IFERROR(IF(A2="","",VLOOKUP(A2,INDIRECT("HISTÓRICO COBROS!A3:F"&COUNTA('HISTÓRICO COBROS'!A:A)),6,FALSE)),"")} -> 33.284 | H2: =IF(D2="","",D2+F2) -> 163.234 | I2: =IF(E2="","",E2+G2) -> 163.234 | J2: =IF(D2="","",D2-E2) -> 0 | K2: =IF(F2="","",F2-G2) -> 0
A3: 002-2024 | B3: {=IF(A3="","",VLOOKUP(A3,INDIRECT("CXC!A2:B"&COUNTA(CXC!A:A)),2,FALSE))} -> PINTO Y COMPANIA | C3: {=IF(A3="","",VLOOKUP(A3,INDIRECT("CXC!A2:C"&COUNTA(CXC!A:A)),3,FALSE))} -> 45608 | D3: {=IF(A3="","",VLOOKUP(A3,INDIRECT("CXC!A2:H"&COUNTA(CXC!A:A)),8,FALSE))} -> 67.8 | E3: {=IFERROR(IF(A3="","",VLOOKUP(A3,INDIRECT("HISTÓRICO COBROS!A3:E"&COUNTA('HISTÓRICO COBROS'!A:A)),5,FALSE)),"")} -> 67.8 | F3: {=IF(A3="","",VLOOKUP(A3,INDIRECT("CXC!A2:I"&COUNTA(CXC!A:A)),9,FALSE))} -> 0 | G3: {=IFERROR(IF(A3="","",VLOOKUP(A3,INDIRECT("HISTÓRICO COBROS!A3:F"&COUNTA('HISTÓRICO COBROS'!A:A)),6,FALSE)),"")} -> 0 | H3: =IF(D3="","",D3+F3) -> 67.8 | I3: =IF(E3="","",E3+G3) -> 67.8 | J3: =IF(D3="","",D3-E3) -> 0 | K3: =IF(F3="","",F3-G3) -> 0
A4: 003-2024 | B4: {=IF(A4="","",VLOOKUP(A4,INDIRECT("CXC!A2:B"&COUNTA(CXC!A:A)),2,FALSE))} -> DIVACO | C4: {=IF(A4="","",VLOOKUP(A4,INDIRECT("CXC!A2:C"&COUNTA(CXC!A:A)),3,FALSE))} -> 45608 | D4: {=IF(A4="","",VLOOKUP(A4,INDIRECT("CXC!A2:H"&COUNTA(CXC!A:A)),8,FALSE))} -> 79.1 | E4: {=IFERROR(IF(A4="","",VLOOKUP(A4,INDIRECT("HISTÓRICO COBROS!A3:E"&COUNTA('HISTÓRICO COBROS'!A:A)),5,FALSE)),"")} -> 79.1 | F4: {=IF(A4="","",VLOOKUP(A4,INDIRECT("CXC!A2:I"&COUNTA(CXC!A:A)),9,FALSE))} -> 0 | G4: {=IFERROR(IF(A4="","",VLOOKUP(A4,INDIRECT("HISTÓRICO COBROS!A3:F"&COUNTA('HISTÓRICO COBROS'!A:A)),6,FALSE)),"")} -> 0 | H4: =IF(D4="","",D4+F4) -> 79.1 | I4: =IF(E4="","",E4+G4) -> 79.1 | J4: =IF(D4="","",D4-E4) -> 0 | K4: =IF(F4="","",F4-G4) -> 0
A5: 004-2024 | B5: {=IF(A5="","",VLOOKUP(A5,INDIRECT("CXC!A2:B"&COUNTA(CXC!A:A)),2,FALSE))} -> DIGICEL | C5: {=IF(A5="","",VLOOKUP(A5,INDIRECT("CXC!A2:C"&COUNTA(CXC!A:A)),3,FALSE))} -> 45609 | D5: {=IF(A5="","",VLOOKUP(A5,INDIRECT("CXC!A2:H"&COUNTA(CXC!A:A)),8,FALSE))} -> 113 | E5: {=IFERROR(IF(A5="","",VLOOKUP(A5,INDIRECT("HISTÓRICO COBROS!A3:E"&COUNTA('HISTÓRICO COBROS'!A:A)),5,FALSE)),"")} -> 113 | F5: {=IF(A5="","",VLOOKUP(A5,INDIRECT("CXC!A2:I"&COUNTA(CXC!A:A)),9,FALSE))} -> 0 | G5: {=IFERROR(IF(A5="","",VLOOKUP(A5,INDIRECT("HISTÓRICO COBROS!A3:F"&COUNTA('HISTÓRICO COBROS'!A:A)),6,FALSE)),"")} -> 0 | H5: =IF(D5="","",D5+F5) -> 113 | I5: =IF(E5="","",E5+G5) -> 113 | J5: =IF(D5="","",D5-E5) -> 0 | K5: =IF(F5="","",F5-G5) -> 0
A6: 005-2024 | B6: {=IF(A6="","",VLOOKUP(A6,INDIRECT("CXC!A2:B"&COUNTA(CXC!A:A)),2,FALSE))} -> AISAL | C6: {=IF(A6="","",VLOOKUP(A6,INDIRECT("CXC!A2:C"&COUNTA(CXC!A:A)),3,FALSE))} -> 45609 | D6: {=IF(A6="","",VLOOKUP(A6,INDIRECT("CXC!A2:H"&COUNTA(CXC!A:A)),8,FALSE))} -> 50.59 | E6: {=IFERROR(IF(A6="","",VLOOKUP(A6,INDIRECT("HISTÓRICO COBROS!A3:E"&COUNTA('HISTÓRICO COBROS'!A:A)),5,FALSE)),"")} | F6: {=IF(A6="","",VLOOKUP(A6,INDIRECT("CXC!A2:I"&COUNTA(CXC!A:A)),9,FALSE))} -> 53.55 | G6: {=IFERROR(IF(A6="","",VLOOKUP(A6,INDIRECT("HISTÓRICO COBROS!A3:F"&COUNTA('HISTÓRICO COBROS'!A:A)),6,FALSE)),"")} | H6: =IF(D6="","",D6+F6) -> 104.14 | I6: =IF(E6="","",E6+G6) | J6: =IF(D6="","",D6-E6) -> 50.59 | K6: =IF(F6="","",F6-G6) -> 53.55
A7: 006-2024 | B7: {=IF(A7="","",VLOOKUP(A7,INDIRECT("CXC!A2:B"&COUNTA(CXC!A:A)),2,FALSE))} -> GEVI | C7: {=IF(A7="","",VLOOKUP(A7,INDIRECT("CXC!A2:C"&COUNTA(CXC!A:A)),3,FALSE))} -> 45609 | D7: {=IF(A7="","",VLOOKUP(A7,INDIRECT("CXC!A2:H"&COUNTA(CXC!A:A)),8,FALSE))} -> 25.1 | E7: {=IFERROR(IF(A7="","",VLOOKUP(A7,INDIRECT("HISTÓRICO COBROS!A3:E"&COUNTA('HISTÓRICO COBROS'!A:A)),5,FALSE)),"")} | F7: {=IF(A7="","",VLOOKUP(A7,INDIRECT("CXC!A2:I"&COUNTA(CXC!A:A)),9,FALSE))} -> 30.55 | G7: {=IFERROR(IF(A7="","",VLOOKUP(A7,INDIRECT("HISTÓRICO COBROS!A3:F"&COUNTA('HISTÓRICO COBROS'!A:A)),6,FALSE)),"")} | H7: =IF(D7="","",D7+F7) -> 55.65 | I7: =IF(E7="","",E7+G7) | J7: =IF(D7="","",D7-E7) -> 25.1 | K7: =IF(F7="","",F7-G7) -> 30.55
A8: 007-2024 | B8: {=IF(A8="","",VLOOKUP(A8,INDIRECT("CXC!A2:B"&COUNTA(CXC!A:A)),2,FALSE))} -> AISAL | C8: {=IF(A8="","",VLOOKUP(A8,INDIRECT("CXC!A2:C"&COUNTA(CXC!A:A)),3,FALSE))} -> 45609 | D8: {=IF(A8="","",VLOOKUP(A8,INDIRECT("CXC!A2:H"&COUNTA(CXC!A:A)),8,FALSE))} -> 50.1 | E8: {=IFERROR(IF(A8="","",VLOOKUP(A8,INDIRECT("HISTÓRICO COBROS!A3:E"&COUNTA('HISTÓRICO COBROS'!A:A)),5,FALSE)),"")} | F8: {=IF(A8="","",VLOOKUP(A8,INDIRECT("CXC!A2:I"&COUNTA(CXC!A:A)),9,FALSE))} -> 0 | G8: {=IFERROR(IF(A8="","",VLOOKUP(A8,INDIRECT("HISTÓRICO COBROS!A3:F"&COUNTA('HISTÓRICO COBROS'!A:A)),6,FALSE)),"")} | H8: =IF(D8="","",D8+F8) -> 50.1 | I8: =IF(E8="","",E8+G8) | J8: =IF(D8="","",D8-E8) -> 50.1 | K8: =IF(F8="","",F8-G8) -> 0
A9: 008-2024 | B9: {=IF(A9="","",VLOOKUP(A9,INDIRECT("CXC!A2:B"&COUNTA(CXC!A:A)),2,FALSE))} -> QUIMICA INDUSTRIAL | C9: {=IF(A9="","",VLOOKUP(A9,INDIRECT("CXC!A2:C"&COUNTA(CXC!A:A)),3,FALSE))} -> 45609 | D9: {=IF(A9="","",VLOOKUP(A9,INDIRECT("CXC!A2:H"&COUNTA(CXC!A:A)),8,FALSE))} -> 209.05 | E9: {=IFERROR(IF(A9="","",VLOOKUP(A9,INDIRECT("HISTÓRICO COBROS!A3:E"&COUNTA('HISTÓRICO COBROS'!A:A)),5,FALSE)),"")} -> 209.05 | F9: {=IF(A9="","",VLOOKUP(A9,INDIRECT("CXC!A2:I"&COUNTA(CXC!A:A)),9,FALSE))} -> 91.67 | G9: {=IFERROR(IF(A9="","",VLOOKUP(A9,INDIRECT("HISTÓRICO COBROS!A3:F"&COUNTA('HISTÓRICO COBROS'!A:A)),6,FALSE)),"")} -> 91.67 | H9: =IF(D9="","",D9+F9) -> 300.72 | I9: =IF(E9="","",E9+G9) -> 300.72 | J9: =IF(D9="","",D9-E9) -> 0 | K9: =IF(F9="","",F9-G9) -> 0
B10: {=IF(A10="","",VLOOKUP(A10,INDIRECT("CXC!A2:B"&COUNTA(CXC!A:A)),2,FALSE))} | C10: {=IF(A10="","",VLOOKUP(A10,INDIRECT("CXC!A2:C"&COUNTA(CXC!A:A)),3,FALSE))} | D10: {=IF(A10="","",VLOOKUP(A10,INDIRECT("CXC!A2:H"&COUNTA(CXC!A:A)),8,FALSE))} | E10: {=IFERROR(IF(A10="","",VLOOKUP(A10,INDIRECT("HISTÓRICO COBROS!A3:E"&COUNTA('HISTÓRICO COBROS'!A:A)),5,FALSE)),"")} | F10: {=IF(A10="","",VLOOKUP(A10,INDIRECT("CXC!A2:I"&COUNTA(CXC!A:A)),9,FALSE))} | G10: {=IFERROR(IF(A10="","",VLOOKUP(A10,INDIRECT("HISTÓRICO COBROS!A3:F"&COUNTA('HISTÓRICO COBROS'!A:A)),6,FALSE)),"")} | H10: =IF(D10="","",D10+F10) | I10: =IF(E10="","",E10+G10) | J10: =IF(D10="","",D10-E10) | K10: =IF(F10="","",F10-G10)
B11: {=IF(A11="","",VLOOKUP(A11,INDIRECT("CXC!A2:B"&COUNTA(CXC!A:A)),2,FALSE))} | C11: {=IF(A11="","",VLOOKUP(A11,INDIRECT("CXC!A2:C"&COUNTA(CXC!A:A)),3,FALSE))} | D11: {=IF(A11="","",VLOOKUP(A11,INDIRECT("CXC!A2:H"&COUNTA(CXC!A:A)),8,FALSE))} | E11: {=IFERROR(IF(A11="","",VLOOKUP(A11,INDIRECT("HISTÓRICO COBROS!A3:E"&COUNTA('HISTÓRICO COBROS'!A:A)),5,FALSE)),"")} | F11: {=IF(A11="","",VLOOKUP(A11,INDIRECT("CXC!A2:I"&COUNTA(CXC!A:A)),9,FALSE))} | G11: {=IFERROR(IF(A11="","",VLOOKUP(A11,INDIRECT("HISTÓRICO COBROS!A3:F"&COUNTA('HISTÓRICO COBROS'!A:A)),6,FALSE)),"")} | H11: =IF(D11="","",D11+F11) | I11: =IF(E11="","",E11+G11) | J11: =IF(D11="","",D11-E11) | K11: =IF(F11="","",F11-G11)
B12: {=IF(A12="","",VLOOKUP(A12,INDIRECT("CXC!A2:B"&COUNTA(CXC!A:A)),2,FALSE))} | C12: {=IF(A12="","",VLOOKUP(A12,INDIRECT("CXC!A2:C"&COUNTA(CXC!A:A)),3,FALSE))} | D12: {=IF(A12="","",VLOOKUP(A12,INDIRECT("CXC!A2:H"&COUNTA(CXC!A:A)),8,FALSE))} | E12: {=IFERROR(IF(A12="","",VLOOKUP(A12,INDIRECT("HISTÓRICO COBROS!A3:E"&COUNTA('HISTÓRICO COBROS'!A:A)),5,FALSE)),"")} | F12: {=IF(A12="","",VLOOKUP(A12,INDIRECT("CXC!A2:I"&COUNTA(CXC!A:A)),9,FALSE))} | G12: {=IFERROR(IF(A12="","",VLOOKUP(A12,INDIRECT("HISTÓRICO COBROS!A3:F"&COUNTA('HISTÓRICO COBROS'!A:A)),6,FALSE)),"")} | H12: =IF(D12="","",D12+F12) | I12: =IF(E12="","",E12+G12) | J12: =IF(D12="","",D12-E12) | K12: =IF(F12="","",F12-G12)
B13: {=IF(A13="","",VLOOKUP(A13,INDIRECT("CXC!A2:B"&COUNTA(CXC!A:A)),2,FALSE))} | C13: {=IF(A13="","",VLOOKUP(A13,INDIRECT("CXC!A2:C"&COUNTA(CXC!A:A)),3,FALSE))} | D13: {=IF(A13="","",VLOOKUP(A13,INDIRECT("CXC!A2:H"&COUNTA(CXC!A:A)),8,FALSE))} | E13: {=IFERROR(IF(A13="","",VLOOKUP(A13,INDIRECT("HISTÓRICO COBROS!A3:E"&COUNTA('HISTÓRICO COBROS'!A:A)),5,FALSE)),"")} | F13: {=IF(A13="","",VLOOKUP(A13,INDIRECT("CXC!A2:I"&COUNTA(CXC!A:A)),9,FALSE))} | G13: {=IFERROR(IF(A13="","",VLOOKUP(A13,INDIRECT("HISTÓRICO COBROS!A3:F"&COUNTA('HISTÓRICO COBROS'!A:A)),6,FALSE)),"")} | H13: =IF(D13="","",D13+F13) | I13: =IF(E13="","",E13+G13) | J13: =IF(D13="","",D13-E13) | K13: =IF(F13="","",F13-G13)
B14: {=IF(A14="","",VLOOKUP(A14,INDIRECT("CXC!A2:B"&COUNTA(CXC!A:A)),2,FALSE))} | C14: {=IF(A14="","",VLOOKUP(A14,INDIRECT("CXC!A2:C"&COUNTA(CXC!A:A)),3,FALSE))} | D14: {=IF(A14="","",VLOOKUP(A14,INDIRECT("CXC!A2:H"&COUNTA(CXC!A:A)),8,FALSE))} | E14: {=IFERROR(IF(A14="","",VLOOKUP(A14,INDIRECT("HISTÓRICO COBROS!A3:E"&COUNTA('HISTÓRICO COBROS'!A:A)),5,FALSE)),"")} | F14: {=IF(A14="","",VLOOKUP(A14,INDIRECT("CXC!A2:I"&COUNTA(CXC!A:A)),9,FALSE))} | G14: {=IFERROR(IF(A14="","",VLOOKUP(A14,INDIRECT("HISTÓRICO COBROS!A3:F"&COUNTA('HISTÓRICO COBROS'!A:A)),6,FALSE)),"")} | H14: =IF(D14="","",D14+F14) | I14: =IF(E14="","",E14+G14) | J14: =IF(D14="","",D14-E14) | K14: =IF(F14="","",F14-G14)
B15: {=IF(A15="","",VLOOKUP(A15,INDIRECT("CXC!A2:B"&COUNTA(CXC!A:A)),2,FALSE))} | C15: {=IF(A15="","",VLOOKUP(A15,INDIRECT("CXC!A2:C"&COUNTA(CXC!A:A)),3,FALSE))} | D15: {=IF(A15="","",VLOOKUP(A15,INDIRECT("CXC!A2:H"&COUNTA(CXC!A:A)),8,FALSE))} | E15: {=IFERROR(IF(A15="","",VLOOKUP(A15,INDIRECT("HISTÓRICO COBROS!A3:E"&COUNTA('HISTÓRICO COBROS'!A:A)),5,FALSE)),"")} | F15: {=IF(A15="","",VLOOKUP(A15,INDIRECT("CXC!A2:I"&COUNTA(CXC!A:A)),9,FALSE))} | G15: {=IFERROR(IF(A15="","",VLOOKUP(A15,INDIRECT("HISTÓRICO COBROS!A3:F"&COUNTA('HISTÓRICO COBROS'!A:A)),6,FALSE)),"")} | H15: =IF(D15="","",D15+F15) | I15: =IF(E15="","",E15+G15) | J15: =IF(D15="","",D15-E15) | K15: =IF(F15="","",F15-G15)
B16: {=IF(A16="","",VLOOKUP(A16,INDIRECT("CXC!A2:B"&COUNTA(CXC!A:A)),2,FALSE))} | C16: {=IF(A16="","",VLOOKUP(A16,INDIRECT("CXC!A2:C"&COUNTA(CXC!A:A)),3,FALSE))} | D16: {=IF(A16="","",VLOOKUP(A16,INDIRECT("CXC!A2:H"&COUNTA(CXC!A:A)),8,FALSE))} | E16: {=IFERROR(IF(A16="","",VLOOKUP(A16,INDIRECT("HISTÓRICO COBROS!A3:E"&COUNTA('HISTÓRICO COBROS'!A:A)),5,FALSE)),"")} | F16: {=IF(A16="","",VLOOKUP(A16,INDIRECT("CXC!A2:I"&COUNTA(CXC!A:A)),9,FALSE))} | G16: {=IFERROR(IF(A16="","",VLOOKUP(A16,INDIRECT("HISTÓRICO COBROS!A3:F"&COUNTA('HISTÓRICO COBROS'!A:A)),6,FALSE)),"")} | H16: =IF(D16="","",D16+F16) | I16: =IF(E16="","",E16+G16) | J16: =IF(D16="","",D16-E16) | K16: =IF(F16="","",F16-G16)
B17: {=IF(A17="","",VLOOKUP(A17,INDIRECT("CXC!A2:B"&COUNTA(CXC!A:A)),2,FALSE))} | C17: {=IF(A17="","",VLOOKUP(A17,INDIRECT("CXC!A2:C"&COUNTA(CXC!A:A)),3,FALSE))} | D17: {=IF(A17="","",VLOOKUP(A17,INDIRECT("CXC!A2:H"&COUNTA(CXC!A:A)),8,FALSE))} | E17: {=IFERROR(IF(A17="","",VLOOKUP(A17,INDIRECT("HISTÓRICO COBROS!A3:E"&COUNTA('HISTÓRICO COBROS'!A:A)),5,FALSE)),"")} | F17: {=IF(A17="","",VLOOKUP(A17,INDIRECT("CXC!A2:I"&COUNTA(CXC!A:A)),9,FALSE))} | G17: {=IFERROR(IF(A17="","",VLOOKUP(A17,INDIRECT("HISTÓRICO COBROS!A3:F"&COUNTA('HISTÓRICO COBROS'!A:A)),6,FALSE)),"")} | H17: =IF(D17="","",D17+F17) | I17: =IF(E17="","",E17+G17) | J17: =IF(D17="","",D17-E17) | K17: =IF(F17="","",F17-G17)
B18: {=IF(A18="","",VLOOKUP(A18,INDIRECT("CXC!A2:B"&COUNTA(CXC!A:A)),2,FALSE))} | C18: {=IF(A18="","",VLOOKUP(A18,INDIRECT("CXC!A2:C"&COUNTA(CXC!A:A)),3,FALSE))} | D18: {=IF(A18="","",VLOOKUP(A18,INDIRECT("CXC!A2:H"&COUNTA(CXC!A:A)),8,FALSE))} | E18: {=IFERROR(IF(A18="","",VLOOKUP(A18,INDIRECT("HISTÓRICO COBROS!A3:E"&COUNTA('HISTÓRICO COBROS'!A:A)),5,FALSE)),"")} | F18: {=IF(A18="","",VLOOKUP(A18,INDIRECT("CXC!A2:I"&COUNTA(CXC!A:A)),9,FALSE))} | G18: {=IFERROR(IF(A18="","",VLOOKUP(A18,INDIRECT("HISTÓRICO COBROS!A3:F"&COUNTA('HISTÓRICO COBROS'!A:A)),6,FALSE)),"")} | H18: =IF(D18="","",D18+F18) | I18: =IF(E18="","",E18+G18) | J18: =IF(D18="","",D18-E18) | K18: =IF(F18="","",F18-G18)
B19: {=IF(A19="","",VLOOKUP(A19,INDIRECT("CXC!A2:B"&COUNTA(CXC!A:A)),2,FALSE))} | C19: {=IF(A19="","",VLOOKUP(A19,INDIRECT("CXC!A2:C"&COUNTA(CXC!A:A)),3,FALSE))} | D19: {=IF(A19="","",VLOOKUP(A19,INDIRECT("CXC!A2:H"&COUNTA(CXC!A:A)),8,FALSE))} | E19: {=IFERROR(IF(A19="","",VLOOKUP(A19,INDIRECT("HISTÓRICO COBROS!A3:E"&COUNTA('HISTÓRICO COBROS'!A:A)),5,FALSE)),"")} | F19: {=IF(A19="","",VLOOKUP(A19,INDIRECT("CXC!A2:I"&COUNTA(CXC!A:A)),9,FALSE))} | G19: {=IFERROR(IF(A19="","",VLOOKUP(A19,INDIRECT("HISTÓRICO COBROS!A3:F"&COUNTA('HISTÓRICO COBROS'!A:A)),6,FALSE)),"")} | H19: =IF(D19="","",D19+F19) | I19: =IF(E19="","",E19+G19) | J19: =IF(D19="","",D19-E19) | K19: =IF(F19="","",F19-G19)
B20: {=IF(A20="","",VLOOKUP(A20,INDIRECT("CXC!A2:B"&COUNTA(CXC!A:A)),2,FALSE))} | C20: {=IF(A20="","",VLOOKUP(A20,INDIRECT("CXC!A2:C"&COUNTA(CXC!A:A)),3,FALSE))} | D20: {=IF(A20="","",VLOOKUP(A20,INDIRECT("CXC!A2:H"&COUNTA(CXC!A:A)),8,FALSE))} | E20: {=IFERROR(IF(A20="","",VLOOKUP(A20,INDIRECT("HISTÓRICO COBROS!A3:E"&COUNTA('HISTÓRICO COBROS'!A:A)),5,FALSE)),"")} | F20: {=IF(A20="","",VLOOKUP(A20,INDIRECT("CXC!A2:I"&COUNTA(CXC!A:A)),9,FALSE))} | G20: {=IFERROR(IF(A20="","",VLOOKUP(A20,INDIRECT("HISTÓRICO COBROS!A3:F"&COUNTA('HISTÓRICO COBROS'!A:A)),6,FALSE)),"")} | H20: =IF(D20="","",D20+F20) | I20: =IF(E20="","",E20+G20) | J20: =IF(D20="","",D20-E20) | K20: =IF(F20="","",F20-G20)
B21: {=IF(A21="","",VLOOKUP(A21,INDIRECT("CXC!A2:B"&COUNTA(CXC!A:A)),2,FALSE))} | C21: {=IF(A21="","",VLOOKUP(A21,INDIRECT("CXC!A2:C"&COUNTA(CXC!A:A)),3,FALSE))} | D21: {=IF(A21="","",VLOOKUP(A21,INDIRECT("CXC!A2:H"&COUNTA(CXC!A:A)),8,FALSE))} | E21: {=IFERROR(IF(A21="","",VLOOKUP(A21,INDIRECT("HISTÓRICO COBROS!A3:E"&COUNTA('HISTÓRICO COBROS'!A:A)),5,FALSE)),"")} | F21: {=IF(A21="","",VLOOKUP(A21,INDIRECT("CXC!A2:I"&COUNTA(CXC!A:A)),9,FALSE))} | G21: {=IFERROR(IF(A21="","",VLOOKUP(A21,INDIRECT("HISTÓRICO COBROS!A3:F"&COUNTA('HISTÓRICO COBROS'!A:A)),6,FALSE)),"")} | H21: =IF(D21="","",D21+F21) | I21: =IF(E21="","",E21+G21) | J21: =IF(D21="","",D21-E21) | K21: =IF(F21="","",F21-G21)
... B1000: {=IF(A1000="","",VLOOKUP(A1000,INDIRECT("CXC!A2:B"&COUNTA(CXC!A:A)),2,FALSE))} | C1000: {=IF(A1000="","",VLOOKUP(A1000,INDIRECT("CXC!A2:C"&COUNTA(CXC!A:A)),3,FALSE))} | D1000: {=IF(A1000="","",VLOOKUP(A1000,INDIRECT("CXC!A2:H"&COUNTA(CXC!A:A)),8,FALSE))} | E1000: {=IFERROR(IF(A1000="","",VLOOKUP(A1000,INDIRECT("HISTÓRICO COBROS!A3:E"&COUNTA('HISTÓRICO COBROS'!A:A)),5,FALSE)),"")} | F1000: {=IF(A1000="","",VLOOKUP(A1000,INDIRECT("CXC!A2:I"&COUNTA(CXC!A:A)),9,FALSE))} | G1000: {=IFERROR(IF(A1000="","",VLOOKUP(A1000,INDIRECT("HISTÓRICO COBROS!A3:F"&COUNTA('HISTÓRICO COBROS'!A:A)),6,FALSE)),"")} | H1000: =IF(D1000="","",D1000+F1000) | I1000: =IF(E1000="","",E1000+G1000) | J1000: =IF(D1000="","",D1000-E1000) | K1000: =IF(F1000="","",F1000-G1000)

Sheet BUSQUEDAS
A1: BÚSQUEDA PERSONALIZADA
A3: Buscar Por OS | B3: 001-2024
A5: =IFERROR(__xludf.DUMMYFUNCTION("QUERY('BASE TRANSFERENCIAS'!A:K,""select * where A contains '""&B3&""' or B contains '""&B3&""'"",1)"),"OS") -> OS | B5: =IFERROR(__xludf.DUMMYFUNCTION("""COMPUTED_VALUE"""),"CLIENTE") -> CLIENTE | C5: =IFERROR(__xludf.DUMMYFUNCTION("""COMPUTED_VALUE"""),"SUB CLIENTE") -> SUB CLIENTE | D5: =IFERROR(__xludf.DUMMYFUNCTION("""COMPUTED_VALUE"""),"A NOMBRE DE") -> A NOMBRE DE | E5: =IFERROR(__xludf.DUMMYFUNCTION("""COMPUTED_VALUE"""),"DETALLE") -> DETALLE | F5: =IFERROR(__xludf.DUMMYFUNCTION("""COMPUTED_VALUE"""),"CCF") -> CCF | G5: =IFERROR(__xludf.DUMMYFUNCTION("""COMPUTED_VALUE"""),"MONTO") -> MONTO | H5: =IFERROR(__xludf.DUMMYFUNCTION("""COMPUTED_VALUE"""),"SOLICITADO POR") -> SOLICITADO POR | I5: =IFERROR(__xludf.DUMMYFUNCTION("""COMPUTED_VALUE"""),"BANCO") -> BANCO | J5: =IFERROR(__xludf.DUMMYFUNCTION("""COMPUTED_VALUE"""),"TIPO") -> TIPO | K5: =IFERROR(__xludf.DUMMYFUNCTION("""COMPUTED_VALUE"""),"FECHA") -> FECHA
A6: =IFERROR(__xludf.DUMMYFUNCTION("""COMPUTED_VALUE"""),"001-2024") -> 001-2024 | B6: =IFERROR(__xludf.DUMMYFUNCTION("""COMPUTED_VALUE"""),"PANADERIA SINAI") -> PANADERIA SINAI | C6: =IFERROR(__xludf.DUMMYFUNCTION("""COMPUTED_VALUE"""),"N/A") -> N/A | D6: =IFERROR(__xludf.DUMMYFUNCTION("""COMPUTED_VALUE"""),"M.H") -> M.H | E6: =IFERROR(__xludf.DUMMYFUNCTION("""COMPUTED_VALUE"""),"IMPUESTOS") -> IMPUESTOS | G6: =IFERROR(__xludf.DUMMYFUNCTION("""COMPUTED_VALUE"""),33.284) -> 33.284 | H6: =IFERROR(__xludf.DUMMYFUNCTION("""COMPUTED_VALUE"""),"MARÍA JOSE") -> MARÍA JOSE | I6: =IFERROR(__xludf.DUMMYFUNCTION("""COMPUTED_VALUE"""),"AGRICOLA") -> AGRICOLA | J6: =IFERROR(__xludf.DUMMYFUNCTION("""COMPUTED_VALUE"""),"CARGOS A CLIENTES") -> CARGOS A CLIENTES | K6: =IFERROR(__xludf.DUMMYFUNCTION("""COMPUTED_VALUE"""),45606.0) -> 45606

Sheet LISTAS
A1: Aforadores | B1: Clientes | C1: Bancos | D1: Tipo de Gasto | E1: OS | F1: Tipo de Factura | G1: Tipo de Pago
A2: ADELAYDA | B2: EFL | C2: AGRICOLA | D2: CARGOS A CLIENTES | E2: =IFERROR(__xludf.DUMMYFUNCTION("ARRAYFORMULA({""ADMON""; FILTER(ListaOS, LEN(ListaOS) > 0)}) "),"ADMON") -> ADMON | F2: DTE | G2: TRANSFERENCIA
A3: GLENDA CAÑAS | B3: SERTAGRI | C3: DAVIVIENDA | D3: COSTO | E3: =IFERROR(__xludf.DUMMYFUNCTION("""COMPUTED_VALUE"""),"001-2024") -> 001-2024 | F3: FEX | G3: EFECTIVO
A4: MARÍA JOSE | B4: PANADERIA SINAI | C4: CHEQUE | D4: GASTOS DE OPERACIÓN | E4: =IFERROR(__xludf.DUMMYFUNCTION("""COMPUTED_VALUE"""),"002-2024") -> 002-2024 | G4: CHEQUE
A5: ROBERTO | B5: DIGICEL | E5: =IFERROR(__xludf.DUMMYFUNCTION("""COMPUTED_VALUE"""),"003-2024") -> 003-2024
B6: DIVACO | E6: =IFERROR(__xludf.DUMMYFUNCTION("""COMPUTED_VALUE"""),"004-2024") -> 004-2024
B7: TRANSTAINER | E7: =IFERROR(__xludf.DUMMYFUNCTION("""COMPUTED_VALUE"""),"005-2024") -> 005-2024
B8: FERRETERIA TIO WILLIS | E8: =IFERROR(__xludf.DUMMYFUNCTION("""COMPUTED_VALUE"""),"006-2024") -> 006-2024
B9: DANIEL MONTERROZA | E9: =IFERROR(__xludf.DUMMYFUNCTION("""COMPUTED_VALUE"""),"007-2024") -> 007-2024
B10: PINTO Y COMPANIA | E10: =IFERROR(__xludf.DUMMYFUNCTION("""COMPUTED_VALUE"""),"008-2024") -> 008-2024
B11: GEVI
B12: SERTAGRI
B13: HAROLD CALDERON
B14: PINTO Y COMPAÑIA
B15: MEDICALD
B16: IMPORTADORA MILKY
B17: ALIMENTOS MADRE TIERRA
B18: TRANSTAINER
B19: AISAL
B20: QUIMICA INDUSTRIAL
B21: SOLVI
B22: AVICOLA
B23: POLLO CAMPESTRE

Sheet DATOS_GRAFICO
A1: =IFERROR(__xludf.DUMMYFUNCTION("QUERY( 'BASE OS'!A:H, ""SELECT E, COUNT(A) GROUP BY E ORDER BY COUNT(A) DESC LIMIT 4"", 0 )"),"") | B1: =IFERROR(__xludf.DUMMYFUNCTION("""COMPUTED_VALUE"""),"count ") -> count
A2: =IFERROR(__xludf.DUMMYFUNCTION("""COMPUTED_VALUE"""),"ADELAYDA") -> ADELAYDA | B2: =IFERROR(__xludf.DUMMYFUNCTION("""COMPUTED_VALUE"""),2.0) -> 2
A3: =IFERROR(__xludf.DUMMYFUNCTION("""COMPUTED_VALUE"""),"GLENDA CAÑAS") -> GLENDA CAÑAS | B3: =IFERROR(__xludf.DUMMYFUNCTION("""COMPUTED_VALUE"""),2.0) -> 2
A4: =IFERROR(__xludf.DUMMYFUNCTION("""COMPUTED_VALUE"""),"MARÍA JOSE") -> MARÍA JOSE | B4: =IFERROR(__xludf.DUMMYFUNCTION("""COMPUTED_VALUE"""),2.0) -> 2
A5: =IFERROR(__xludf.DUMMYFUNCTION("""COMPUTED_VALUE"""),"ROBERTO") -> ROBERTO | B5: =IFERROR(__xludf.DUMMYFUNCTION("""COMPUTED_VALUE"""),2.0) -> 2

Sheet TARIFARIO
A1: CODIGO | B1: CLIENTE | C1: SERVICIO | D1: MONTO SIN IVA | F1: SERVICIOS PARA OTROS CLIENTES | I1: LISTA DE SERVICIOS POR CLIENTE SELECCIONADO
A2: AISAL | B2: ALIMENTO IMPORTADOS SUPERIORES DE EL SALVADOR, S.A DE C.V | C2: ASESORIA Y GESTION ADUANERA | D2: 90 | F2: SERVICIO | G2: PRECIO | I2: =IFERROR(__xludf.DUMMYFUNCTION("IF(COUNTIF(A2:A1000, 'CALCULO COBROS'!D4) > 0, {FILTER(C:D, A:A = 'CALCULO COBROS'!D4); F3:G1000}, ARRAYFORMULA(F3:G100) )"),"")
A3: AISAL | B3: ALIMENTO IMPORTADOS SUPERIORES DE EL SALVADOR, S.A DE C.V | C3: ASESORIA Y GESTION ADUANERA GT | D3: 45 | F3: ASESORÍA Y GESTIÓN ADUANAL - OTRO | G3: 0
A4: AISAL | B4: ALIMENTO IMPORTADOS SUPERIORES DE EL SALVADOR, S.A DE C.V | C4: GESTION DE PERMISO DE SALUD | D4: 25 | F4: DECLARACIÓN ESCALONADA - OTRO | G4: 0
A5: AISAL | B5: ALIMENTO IMPORTADOS SUPERIORES DE EL SALVADOR, S.A DE C.V | C5: SERVICIO POR TIEMPO EXTRAORDINARIO | D5: 25 | F5: ELABORACIÓN DUCA T - OTRO | G5: 0
A6: AISAL | B6: ALIMENTO IMPORTADOS SUPERIORES DE EL SALVADOR, S.A DE C.V | C6: GESTION POR SELECTIVO ROJO | D6: 25 | F6: GESTIÓN DE PERMISO DE SALUD - OTRO | G6: 0
A7: AISAL | B7: ALIMENTO IMPORTADOS SUPERIORES DE EL SALVADOR, S.A DE C.V | C7: SERVICIO DE CUADRILLA SAN CRISTOBAL | D7: 150 | F7: GESTIÓN POR MULTA - OTRO | G7: 0
A8: AISAL | B8: ALIMENTO IMPORTADOS SUPERIORES DE EL SALVADOR, S.A DE C.V | C8: REGISTRO SANITARIO POR PRODUCTO | D8: 100 | F8: GESTIÓN POR SELECTIVO ROJO - OTRO | G8: 0
A9: AISAL | B9: ALIMENTO IMPORTADOS SUPERIORES DE EL SALVADOR, S.A DE C.V | C9: TRANSPORTE LOCAL CLG (OFI BODEGA) | D9: 130 | F9: GESTIÓN REVISIÓN DAN - OTRO | G9: 0
A10: ADVANCE | B10: ADVANCE BS EL SALVADOR, S.A DE C.V | C10: ASESORIA Y GESTION ADUANERA | D10: 90 | F10: REGISTRO SANITARIO POR PRODUCTO - OTRO | G10: 0
A11: ADVANCE | B11: ADVANCE BS EL SALVADOR, S.A DE C.V | C11: GESTION DE PERMISO DE SALUD | D11: 25 | F11: SERVICIO DE CUADRILLA - OTRO | G11: 0
A12: ADIMACON | B12: ADIMACON, S.A DE C.V | C12: ASESORIA Y GESTION ADUANERA AMATILLO SV | D12: 95 | F12: TRANSPORTE LOCAL - OTRO | G12: 0
A13: ADIMACON | B13: ADIMACON, S.A DE C.V | C13: ASESORIA Y GESTION ADUANERA AMATILLO HN | D13: 25
A14: ADIMACON | B14: ADIMACON, S.A DE C.V | C14: ASESORIA Y GESTION ADUANERA ACAJUTLA | D14: 80
A15: ADIMACON | B15: ADIMACON, S.A DE C.V | C15: GESTION REVISION DAN | D15: 20
A16: ADIMACON | B16: ADIMACON, S.A DE C.V | C16: GESTION POR SELECTIVO ROJO | D16: 25
A17: ENERLAND | B17: ENERLAND GROUP EL SALVADOR, S.A DE C.V | C17: TRANSPORTE LOCAL INGENIO JIBOA | D17: 465
A18: ENERLAND | B18: ENERLAND GROUP EL SALVADOR, S.A DE C.V | C18: TRANSPORTE LOCAL SOLAR INTERNACIONAL | D18: 295
A19: ENERLAND | B19: ENERLAND GROUP EL SALVADOR, S.A DE C.V | C19: SELECTIVO ROJO | D19: 35
A20: ENERLAND | B20: ENERLAND GROUP EL SALVADOR, S.A DE C.V | C20: MOVIMIENTO POR ESCALONADO | D20: 110
A21: ENERLAND | B21: ENERLAND GROUP EL SALVADOR, S.A DE C.V | C21: DECLARACION ESCALONADA | D21: 180
A22: ENERLAND | B22: ENERLAND GROUP EL SALVADOR, S.A DE C.V | C22: ESTADIA | D22: 50
A23: ENERLAND | B23: ENERLAND GROUP EL SALVADOR, S.A DE C.V | C23: ASESORIA Y GESTION ADUANERA | D23: 85
A24: ENERLAND | B24: ENERLAND GROUP EL SALVADOR, S.A DE C.V | C24: PRESENTACION DE ESCRITO POR AGRUPACION DE BL | D24: 50
... A120: AVICOLA | B120: AVICOLA CAMPESTRE, S.A DE C.V | C120: TRANSPOTR LOCAL EQUIPO DE 8 TONELADAS | D120: 260
I882: =IFERROR(__xludf.DUMMYFUNCTION("""COMPUTED_VALUE"""),"ASESORÍA Y GESTIÓN ADUANAL - OTRO") -> ASESORÍA Y GESTIÓN ADUANAL - OTRO | J882: =IFERROR(__xludf.DUMMYFUNCTION("""COMPUTED_VALUE"""),0.0) -> 0
I883: =IFERROR(__xludf.DUMMYFUNCTION("""COMPUTED_VALUE"""),"DECLARACIÓN ESCALONADA - OTRO") -> DECLARACIÓN ESCALONADA - OTRO | J883: =IFERROR(__xludf.DUMMYFUNCTION("""COMPUTED_VALUE"""),0.0) -> 0
I884: =IFERROR(__xludf.DUMMYFUNCTION("""COMPUTED_VALUE"""),"ELABORACIÓN DUCA T - OTRO") -> ELABORACIÓN DUCA T - OTRO | J884: =IFERROR(__xludf.DUMMYFUNCTION("""COMPUTED_VALUE"""),0.0) -> 0
I885: =IFERROR(__xludf.DUMMYFUNCTION("""COMPUTED_VALUE"""),"GESTIÓN DE PERMISO DE SALUD - OTRO") -> GESTIÓN DE PERMISO DE SALUD - OTRO | J885: =IFERROR(__xludf.DUMMYFUNCTION("""COMPUTED_VALUE"""),0.0) -> 0
I886: =IFERROR(__xludf.DUMMYFUNCTION("""COMPUTED_VALUE"""),"GESTIÓN POR MULTA - OTRO") -> GESTIÓN POR MULTA - OTRO | J886: =IFERROR(__xludf.DUMMYFUNCTION("""COMPUTED_VALUE"""),0.0) -> 0
I887: =IFERROR(__xludf.DUMMYFUNCTION("""COMPUTED_VALUE"""),"GESTIÓN POR SELECTIVO ROJO - OTRO") -> GESTIÓN POR SELECTIVO ROJO - OTRO | J887: =IFERROR(__xludf.DUMMYFUNCTION("""COMPUTED_VALUE"""),0.0) -> 0
I888: =IFERROR(__xludf.DUMMYFUNCTION("""COMPUTED_VALUE"""),"GESTIÓN REVISIÓN DAN - OTRO") -> GESTIÓN REVISIÓN DAN - OTRO | J888: =IFERROR(__xludf.DUMMYFUNCTION("""COMPUTED_VALUE"""),0.0) -> 0
I889: =IFERROR(__xludf.DUMMYFUNCTION("""COMPUTED_VALUE"""),"REGISTRO SANITARIO POR PRODUCTO - OTRO") -> REGISTRO SANITARIO POR PRODUCTO - OTRO | J889: =IFERROR(__xludf.DUMMYFUNCTION("""COMPUTED_VALUE"""),0.0) -> 0
I890: =IFERROR(__xludf.DUMMYFUNCTION("""COMPUTED_VALUE"""),"SERVICIO DE CUADRILLA - OTRO") -> SERVICIO DE CUADRILLA - OTRO | J890: =IFERROR(__xludf.DUMMYFUNCTION("""COMPUTED_VALUE"""),0.0) -> 0
I891: =IFERROR(__xludf.DUMMYFUNCTION("""COMPUTED_VALUE"""),"TRANSPORTE LOCAL - OTRO") -> TRANSPORTE LOCAL - OTRO | J891: =IFERROR(__xludf.DUMMYFUNCTION("""COMPUTED_VALUE"""),0.0) -> 0
